{"orb_combination":[21,8,1],"combo_threshold":7,"threads":4,"cost_time":437.5119819641113,"max_combo":7,"combo_to_board_count":{"7":199},"combo_to_boards":{"7":[{"combo_count":7,"main_combo_count":5,"drop_times":4,"combos":[[6,7],[6,5],[6,3],[1,3],[6,3],[1,3],[6,3]],"board":["6 6 1 6 6 6","6 1 6 6 1 1","6 6 6 1 6 6","6 1 2 6 6 6","6 1 6 6 1 6"],"matched_count":27,"matched_main_count":21,"matched_other_count":6,"main_damage_multiplier":16.25,"simulation_times":10000,"combo_count_avg":8.5657,"combo_count_min":6,"main_combo_count_avg":5.163,"main_damage_multiplier_avg":19.71045625},{"combo_count":7,"main_combo_count":5,"drop_times":3,"combos":[[6,3],[6,9],[6,3],[1,4],[6,3],[1,3],[6,3]],"board":["6 6 6 1 6 6","1 6 1 6 1 1","6 1 6 6 6 6","6 6 2 1 6 6","6 6 1 6 6 6"],"matched_count":28,"matched_main_count":21,"matched_other_count":7,"main_damage_multiplier":16.25,"simulation_times":10000,"combo_count_avg":8.2727,"combo_count_min":6,"main_combo_count_avg":5.1541,"main_damage_multiplier_avg":19.24508125},{"combo_count":7,"main_combo_count":5,"drop_times":3,"combos":[[6,3],[6,9],[6,3],[1,3],[6,3],[1,3],[6,3]],"board":["6 6 6 1 6 6","1 6 1 6 1 1","6 1 6 6 6 6","6 6 1 1 6 6","6 6 2 6 6 6"],"matched_count":27,"matched_main_count":21,"matched_other_count":6,"main_damage_multiplier":16.25,"simulation_times":10000,"combo_count_avg":8.2321,"combo_count_min":6,"main_combo_count_avg":5.1586,"main_damage_multiplier_avg":19.12453125},{"combo_count":7,"main_combo_count":5,"drop_times":3,"combos":[[6,3],[6,4],[6,7],[6,3],[1,3],[1,3],[6,3]],"board":["6 6 6 1 6 6","1 6 1 6 6 6","6 1 6 1 6 6","6 6 1 6 1 2","6 1 6 6 6 6"],"matched_count":26,"matched_main_count":20,"matched_other_count":6,"main_damage_multiplier":15.625,"simulation_times":10000,"combo_count_avg":8.4568,"combo_count_min":6,"main_combo_count_avg":5.265,"main_damage_multiplier_avg":19.1129},{"combo_count":7,"main_combo_count":5,"drop_times":3,"combos":[[6,3],[6,3],[6,8],[6,3],[1,3],[1,3],[6,3]],"board":["6 6 1 6 6 6","6 6 6 1 6 1","6 6 1 6 1 6","6 1 6 1 6 6","2 6 6 6 1 6"],"matched_count":26,"matched_main_count":20,"matched_other_count":6,"main_damage_multiplier":15.625,"simulation_times":10000,"combo_count_avg":8.4428,"combo_count_min":6,"main_combo_count_avg":5.2595,"main_damage_multiplier_avg":19.05745625},{"combo_count":7,"main_combo_count":5,"drop_times":4,"combos":[[6,3],[6,4],[6,7],[6,3],[1,3],[6,3],[1,4]],"board":["6 6 6 1 6 6","1 6 1 6 6 6","6 2 6 1 6 6","6 6 1 6 1 1","6 1 6 6 6 6"],"matched_count":27,"matched_main_count":20,"matched_other_count":7,"main_damage_multiplier":15.625,"simulation_times":10000,"combo_count_avg":8.492,"combo_count_min":6,"main_combo_count_avg":5.3162,"main_damage_multiplier_avg":19.0543125},{"combo_count":7,"main_combo_count":5,"drop_times":4,"combos":[[6,5],[6,3],[6,3],[6,3],[1,4],[6,4],[1,3]],"board":["6 6 6 1 6 6","1 6 1 6 6 6","6 1 6 6 2 1","6 6 6 1 6 6","6 1 1 6 6 6"],"matched_count":25,"matched_main_count":18,"matched_other_count":7,"main_damage_multiplier":14.375,"simulation_times":10000,"combo_count_avg":8.7994,"combo_count_min":6,"main_combo_count_avg":5.6218,"main_damage_multiplier_avg":19.04089375},{"combo_count":7,"main_combo_count":5,"drop_times":5,"combos":[[6,7],[6,3],[6,3],[1,4],[6,3],[1,3],[6,3]],"board":["6 6 1 6 6 6","1 1 6 1 6 6","6 6 1 6 1 2","6 6 6 1 6 6","6 6 1 6 6 6"],"matched_count":26,"matched_main_count":19,"matched_other_count":7,"main_damage_multiplier":15.0,"simulation_times":10000,"combo_count_avg":8.7109,"combo_count_min":6,"main_combo_count_avg":5.4149,"main_damage_multiplier_avg":19.01375625},{"combo_count":7,"main_combo_count":5,"drop_times":4,"combos":[[6,3],[6,3],[6,8],[6,3],[1,3],[6,3],[1,4]],"board":["6 6 1 6 6 6","6 6 6 1 6 1","6 6 1 6 2 6","6 1 6 1 6 6","1 6 6 6 1 6"],"matched_count":27,"matched_main_count":20,"matched_other_count":7,"main_damage_multiplier":15.625,"simulation_times":10000,"combo_count_avg":8.4758,"combo_count_min":6,"main_combo_count_avg":5.3118,"main_damage_multiplier_avg":19.0106},{"combo_count":7,"main_combo_count":5,"drop_times":5,"combos":[[6,7],[6,3],[6,3],[1,4],[6,3],[1,3],[6,3]],"board":["6 6 6 1 6 6","6 6 1 6 1 1","2 1 6 1 6 6","6 6 6 1 6 6","6 6 1 6 6 6"],"matched_count":26,"matched_main_count":19,"matched_other_count":7,"main_damage_multiplier":15.0,"simulation_times":10000,"combo_count_avg":8.6858,"combo_count_min":6,"main_combo_count_avg":5.4057,"main_damage_multiplier_avg":18.93165625},{"combo_count":7,"main_combo_count":5,"drop_times":3,"combos":[[6,3],[6,3],[6,8],[6,3],[1,3],[1,3],[6,3]],"board":["6 6 1 6 6 6","6 6 6 1 6 1","6 6 2 6 1 6","6 1 6 1 6 6","1 6 6 6 1 6"],"matched_count":26,"matched_main_count":20,"matched_other_count":6,"main_damage_multiplier":15.625,"simulation_times":10000,"combo_count_avg":8.3727,"combo_count_min":6,"main_combo_count_avg":5.2495,"main_damage_multiplier_avg":18.9152625},{"combo_count":7,"main_combo_count":5,"drop_times":4,"combos":[[6,5],[6,3],[6,5],[6,3],[1,4],[6,3],[1,3]],"board":["6 6 6 1 6 6","1 6 1 6 6 6","6 1 6 6 2 6","6 6 6 1 6 1","6 1 1 6 6 6"],"matched_count":26,"matched_main_count":19,"matched_other_count":7,"main_damage_multiplier":15.0,"simulation_times":10000,"combo_count_avg":8.647,"combo_count_min":7,"main_combo_count_avg":5.4312,"main_damage_multiplier_avg":18.91216875},{"combo_count":7,"main_combo_count":5,"drop_times":3,"combos":[[6,3],[6,4],[6,7],[6,3],[1,3],[1,3],[6,3]],"board":["6 6 6 1 6 6","1 6 1 6 6 6","6 1 6 1 6 6","6 6 1 6 2 1","6 1 6 6 6 6"],"matched_count":26,"matched_main_count":20,"matched_other_count":6,"main_damage_multiplier":15.625,"simulation_times":10000,"combo_count_avg":8.3498,"combo_count_min":6,"main_combo_count_avg":5.2574,"main_damage_multiplier_avg":18.91165625},{"combo_count":7,"main_combo_count":5,"drop_times":3,"combos":[[6,3],[6,3],[6,8],[6,3],[1,3],[1,3],[6,3]],"board":["6 6 1 6 6 6","6 6 6 1 6 1","6 6 1 6 1 6","6 2 6 1 6 6","1 6 6 6 1 6"],"matched_count":26,"matched_main_count":20,"matched_other_count":6,"main_damage_multiplier":15.625,"simulation_times":10000,"combo_count_avg":8.3489,"combo_count_min":6,"main_combo_count_avg":5.2554,"main_damage_multiplier_avg":18.9028},{"combo_count":7,"main_combo_count":5,"drop_times":3,"combos":[[6,3],[6,4],[6,7],[6,3],[1,3],[1,3],[6,3]],"board":["6 6 6 1 6 6","1 6 1 6 6 6","6 1 6 2 6 6","6 6 1 6 1 1","6 1 6 6 6 6"],"matched_count":26,"matched_main_count":20,"matched_other_count":6,"main_damage_multiplier":15.625,"simulation_times":10000,"combo_count_avg":8.3448,"combo_count_min":6,"main_combo_count_avg":5.2575,"main_damage_multiplier_avg":18.86985625},{"combo_count":7,"main_combo_count":5,"drop_times":5,"combos":[[6,3],[6,3],[6,6],[1,3],[6,3],[1,3],[6,3]],"board":["6 6 6 6 6 6","6 6 1 6 1 6","2 1 6 1 6 1","6 6 6 1 1 6","6 6 1 6 6 6"],"matched_count":24,"matched_main_count":18,"matched_other_count":6,"main_damage_multiplier":14.375,"simulation_times":10000,"combo_count_avg":8.8604,"combo_count_min":6,"main_combo_count_avg":5.4915,"main_damage_multiplier_avg":18.77996875},{"combo_count":7,"main_combo_count":5,"drop_times":5,"combos":[[6,3],[6,3],[6,6],[1,3],[6,3],[1,3],[6,3]],"board":["6 6 6 6 6 6","6 1 6 1 6 6","1 6 1 6 1 2","6 6 6 1 6 6","6 1 1 6 6 6"],"matched_count":24,"matched_main_count":18,"matched_other_count":6,"main_damage_multiplier":14.375,"simulation_times":10000,"combo_count_avg":8.856,"combo_count_min":6,"main_combo_count_avg":5.488,"main_damage_multiplier_avg":18.75439375},{"combo_count":7,"main_combo_count":5,"drop_times":3,"combos":[[6,7],[6,3],[6,3],[6,3],[1,5],[6,3],[1,3]],"board":["6 6 6 1 6 6","2 1 1 6 6 6","6 6 1 6 1 1","6 6 6 1 6 6","6 6 1 6 6 6"],"matched_count":27,"matched_main_count":19,"matched_other_count":8,"main_damage_multiplier":15.0,"simulation_times":10000,"combo_count_avg":8.3977,"combo_count_min":6,"main_combo_count_avg":5.4134,"main_damage_multiplier_avg":18.67375},{"combo_count":7,"main_combo_count":5,"drop_times":3,"combos":[[6,3],[6,7],[6,3],[1,3],[1,3],[6,3],[6,3]],"board":["6 6 6 1 6 6","1 6 1 6 1 6","6 1 6 6 6 1","6 6 2 1 6 6","6 6 1 6 6 6"],"matched_count":25,"matched_main_count":19,"matched_other_count":6,"main_damage_multiplier":15.0,"simulation_times":10000,"combo_count_avg":8.4181,"combo_count_min":6,"main_combo_count_avg":5.3507,"main_damage_multiplier_avg":18.64046875},{"combo_count":7,"main_combo_count":5,"drop_times":3,"combos":[[6,3],[6,3],[6,7],[6,3],[1,5],[6,3],[1,3]],"board":["6 6 6 1 6 6","6 6 1 6 6 6","1 1 6 1 6 6","6 6 6 1 1 2","6 6 1 6 6 6"],"matched_count":27,"matched_main_count":19,"matched_other_count":8,"main_damage_multiplier":15.0,"simulation_times":10000,"combo_count_avg":8.3871,"combo_count_min":6,"main_combo_count_avg":5.4128,"main_damage_multiplier_avg":18.63924375},{"combo_count":7,"main_combo_count":5,"drop_times":4,"combos":[[6,9],[6,3],[6,3],[1,4],[6,3],[1,3],[6,3]],"board":["1 6 1 6 6 6","6 6 2 6 6 1","6 1 6 1 1 6","6 6 1 6 6 6","1 6 6 6 6 6"],"matched_count":28,"matched_main_count":21,"matched_other_count":7,"main_damage_multiplier":16.25,"simulation_times":10000,"combo_count_avg":8.1537,"combo_count_min":5,"main_combo_count_avg":5.0275,"main_damage_multiplier_avg":18.6035625},{"combo_count":7,"main_combo_count":5,"drop_times":3,"combos":[[6,3],[6,4],[6,7],[6,3],[1,3],[6,3],[1,3]],"board":["6 6 6 2 6 6","1 6 1 6 6 6","6 1 6 1 6 6","6 6 1 6 1 1","6 1 6 6 6 6"],"matched_count":26,"matched_main_count":20,"matched_other_count":6,"main_damage_multiplier":15.625,"simulation_times":10000,"combo_count_avg":8.32,"combo_count_min":6,"main_combo_count_avg":5.2559,"main_damage_multiplier_avg":18.5997625},{"combo_count":7,"main_combo_count":5,"drop_times":5,"combos":[[6,5],[6,3],[6,4],[1,3],[6,3],[1,3],[6,3]],"board":["1 6 6 1 6 6","6 1 6 6 6 6","1 6 1 6 1 2","6 6 6 1 6 6","6 6 1 6 6 6"],"matched_count":24,"matched_main_count":18,"matched_other_count":6,"main_damage_multiplier":14.375,"simulation_times":10000,"combo_count_avg":8.7583,"combo_count_min":6,"main_combo_count_avg":5.4741,"main_damage_multiplier_avg":18.5975625},{"combo_count":7,"main_combo_count":5,"drop_times":4,"combos":[[6,9],[6,3],[6,3],[1,4],[6,3],[1,3],[6,3]],"board":["6 6 1 6 6 6","6 6 2 6 6 1","6 1 6 1 1 6","1 6 1 6 6 6","1 6 6 6 6 6"],"matched_count":28,"matched_main_count":21,"matched_other_count":7,"main_damage_multiplier":16.25,"simulation_times":10000,"combo_count_avg":8.1538,"combo_count_min":6,"main_combo_count_avg":5.017,"main_damage_multiplier_avg":18.5950875},{"combo_count":7,"main_combo_count":5,"drop_times":4,"combos":[[6,9],[6,3],[6,3],[1,4],[6,3],[1,3],[6,3]],"board":["6 6 1 6 6 6","6 6 2 6 6 1","6 1 6 1 1 6","1 6 6 6 6 6","1 6 1 6 6 6"],"matched_count":28,"matched_main_count":21,"matched_other_count":7,"main_damage_multiplier":16.25,"simulation_times":10000,"combo_count_avg":8.1431,"combo_count_min":6,"main_combo_count_avg":5.0219,"main_damage_multiplier_avg":18.58845},{"combo_count":7,"main_combo_count":5,"drop_times":3,"combos":[[6,3],[6,3],[6,8],[6,3],[1,3],[6,3],[1,3]],"board":["6 6 2 6 6 6","6 6 6 1 6 1","6 6 1 6 1 6","6 1 6 1 6 6","1 6 6 6 1 6"],"matched_count":26,"matched_main_count":20,"matched_other_count":6,"main_damage_multiplier":15.625,"simulation_times":10000,"combo_count_avg":8.3017,"combo_count_min":6,"main_combo_count_avg":5.2427,"main_damage_multiplier_avg":18.53},{"combo_count":7,"main_combo_count":5,"drop_times":5,"combos":[[6,5],[6,3],[6,3],[1,3],[6,3],[1,3],[6,3]],"board":["6 6 1 6 6 6","6 1 6 1 6 6","1 6 1 6 1 2","6 6 6 1 6 6","6 6 1 6 6 6"],"matched_count":23,"matched_main_count":17,"matched_other_count":6,"main_damage_multiplier":13.75,"simulation_times":10000,"combo_count_avg":8.895,"combo_count_min":6,"main_combo_count_avg":5.6082,"main_damage_multiplier_avg":18.5179125},{"combo_count":7,"main_combo_count":5,"drop_times":3,"combos":[[6,3],[6,4],[6,5],[1,3],[6,3],[6,3],[1,3]],"board":["6 6 1 6 6 6","1 6 6 1 6 6","6 1 6 1 1 6","6 6 1 6 6 2","6 1 6 6 6 6"],"matched_count":24,"matched_main_count":18,"matched_other_count":6,"main_damage_multiplier":14.375,"simulation_times":10000,"combo_count_avg":8.6745,"combo_count_min":7,"main_combo_count_avg":5.4787,"main_damage_multiplier_avg":18.5174},{"combo_count":7,"main_combo_count":5,"drop_times":5,"combos":[[6,5],[6,3],[6,3],[1,3],[6,3],[1,3],[6,3]],"board":["6 6 6 1 6 6","6 6 1 6 1 6","2 1 6 1 6 1","6 6 6 1 6 6","6 6 1 6 6 6"],"matched_count":23,"matched_main_count":17,"matched_other_count":6,"main_damage_multiplier":13.75,"simulation_times":10000,"combo_count_avg":8.9002,"combo_count_min":6,"main_combo_count_avg":5.5993,"main_damage_multiplier_avg":18.50766875},{"combo_count":7,"main_combo_count":5,"drop_times":3,"combos":[[6,3],[6,4],[6,5],[6,3],[1,3],[1,3],[6,4]],"board":["6 6 6 1 6 6","1 6 1 6 6 6","6 1 6 1 1 6","6 6 1 6 6 2","6 1 6 6 6 6"],"matched_count":25,"matched_main_count":19,"matched_other_count":6,"main_damage_multiplier":15.0,"simulation_times":10000,"combo_count_avg":8.395,"combo_count_min":6,"main_combo_count_avg":5.3251,"main_damage_multiplier_avg":18.442875},{"combo_count":7,"main_combo_count":5,"drop_times":3,"combos":[[6,3],[6,5],[6,5],[1,3],[6,3],[6,3],[1,3]],"board":["6 6 6 1 6 6","6 6 1 6 6 6","6 1 6 6 1 6","1 6 6 1 1 2","6 6 1 6 6 6"],"matched_count":25,"matched_main_count":19,"matched_other_count":6,"main_damage_multiplier":15.0,"simulation_times":10000,"combo_count_avg":8.508,"combo_count_min":7,"main_combo_count_avg":5.3467,"main_damage_multiplier_avg":18.4379},{"combo_count":7,"main_combo_count":5,"drop_times":4,"combos":[[6,9],[6,3],[6,3],[1,3],[6,3],[1,3],[6,3]],"board":["1 6 1 6 6 6","6 6 1 6 6 2","6 1 6 1 1 6","6 6 1 6 6 6","1 6 6 6 6 6"],"matched_count":27,"matched_main_count":21,"matched_other_count":6,"main_damage_multiplier":16.25,"simulation_times":10000,"combo_count_avg":8.1756,"combo_count_min":6,"main_combo_count_avg":4.937,"main_damage_multiplier_avg":18.43449375},{"combo_count":7,"main_combo_count":5,"drop_times":3,"combos":[[6,7],[6,3],[6,3],[6,3],[1,4],[6,3],[1,3]],"board":["6 6 6 1 6 6","1 1 2 6 6 6","6 6 1 6 1 1","6 6 6 1 6 6","6 6 1 6 6 6"],"matched_count":26,"matched_main_count":19,"matched_other_count":7,"main_damage_multiplier":15.0,"simulation_times":10000,"combo_count_avg":8.4007,"combo_count_min":7,"main_combo_count_avg":5.4014,"main_damage_multiplier_avg":18.42400625},{"combo_count":7,"main_combo_count":5,"drop_times":4,"combos":[[6,9],[6,3],[6,3],[1,3],[6,3],[1,3],[6,3]],"board":["6 6 1 6 6 6","6 6 1 6 6 2","6 1 6 1 1 6","1 6 6 6 6 6","1 6 1 6 6 6"],"matched_count":27,"matched_main_count":21,"matched_other_count":6,"main_damage_multiplier":16.25,"simulation_times":10000,"combo_count_avg":8.1638,"combo_count_min":6,"main_combo_count_avg":4.932,"main_damage_multiplier_avg":18.41231875},{"combo_count":7,"main_combo_count":5,"drop_times":4,"combos":[[6,9],[6,3],[6,3],[1,3],[6,3],[1,3],[6,3]],"board":["6 6 1 6 6 6","6 6 1 6 6 2","6 1 6 1 1 6","1 6 1 6 6 6","1 6 6 6 6 6"],"matched_count":27,"matched_main_count":21,"matched_other_count":6,"main_damage_multiplier":16.25,"simulation_times":10000,"combo_count_avg":8.1537,"combo_count_min":6,"main_combo_count_avg":4.9387,"main_damage_multiplier_avg":18.40726875},{"combo_count":7,"main_combo_count":5,"drop_times":4,"combos":[[6,9],[6,3],[6,3],[1,4],[6,3],[1,3],[6,3]],"board":["1 6 1 6 6 6","6 6 1 6 6 1","6 1 6 1 1 6","6 6 1 6 6 6","2 6 6 6 6 6"],"matched_count":28,"matched_main_count":21,"matched_other_count":7,"main_damage_multiplier":16.25,"simulation_times":10000,"combo_count_avg":8.0631,"combo_count_min":5,"main_combo_count_avg":4.9947,"main_damage_multiplier_avg":18.3902625},{"combo_count":7,"main_combo_count":5,"drop_times":4,"combos":[[6,9],[6,3],[6,3],[1,4],[6,3],[1,3],[6,3]],"board":["6 6 1 6 6 6","6 6 1 6 6 1","6 1 6 1 1 6","1 6 6 6 6 6","2 6 1 6 6 6"],"matched_count":28,"matched_main_count":21,"matched_other_count":7,"main_damage_multiplier":16.25,"simulation_times":10000,"combo_count_avg":8.0774,"combo_count_min":5,"main_combo_count_avg":4.9876,"main_damage_multiplier_avg":18.38580625},{"combo_count":7,"main_combo_count":5,"drop_times":4,"combos":[[6,9],[6,3],[6,3],[1,4],[6,3],[1,3],[6,3]],"board":["6 6 1 6 6 6","6 6 1 6 6 1","6 1 6 1 1 6","1 6 1 6 6 6","2 6 6 6 6 6"],"matched_count":28,"matched_main_count":21,"matched_other_count":7,"main_damage_multiplier":16.25,"simulation_times":10000,"combo_count_avg":8.0576,"combo_count_min":5,"main_combo_count_avg":4.9906,"main_damage_multiplier_avg":18.37700625},{"combo_count":7,"main_combo_count":5,"drop_times":4,"combos":[[6,3],[6,3],[6,8],[6,3],[1,3],[6,3],[1,3]],"board":["6 6 1 6 6 6","6 6 6 2 6 1","6 6 1 6 1 6","6 1 6 1 6 6","1 6 6 6 1 6"],"matched_count":26,"matched_main_count":20,"matched_other_count":6,"main_damage_multiplier":15.625,"simulation_times":10000,"combo_count_avg":8.1495,"combo_count_min":6,"main_combo_count_avg":5.2676,"main_damage_multiplier_avg":18.3221125},{"combo_count":7,"main_combo_count":5,"drop_times":4,"combos":[[6,3],[6,4],[6,7],[6,3],[1,3],[6,3],[1,3]],"board":["6 6 6 1 6 6","1 6 2 6 6 6","6 1 6 1 6 6","6 6 1 6 1 1","6 1 6 6 6 6"],"matched_count":26,"matched_main_count":20,"matched_other_count":6,"main_damage_multiplier":15.625,"simulation_times":10000,"combo_count_avg":8.1398,"combo_count_min":6,"main_combo_count_avg":5.2712,"main_damage_multiplier_avg":18.3175875},{"combo_count":7,"main_combo_count":5,"drop_times":4,"combos":[[6,3],[6,3],[6,3],[6,3],[1,3],[6,4],[1,3]],"board":["6 6 6 1 6 6","6 6 1 6 6 6","1 2 6 6 1 1","6 6 6 1 1 6","6 6 1 6 6 6"],"matched_count":22,"matched_main_count":16,"matched_other_count":6,"main_damage_multiplier":13.125,"simulation_times":10000,"combo_count_avg":8.907,"combo_count_min":7,"main_combo_count_avg":5.7949,"main_damage_multiplier_avg":18.2971875},{"combo_count":7,"main_combo_count":5,"drop_times":4,"combos":[[6,9],[6,3],[6,3],[1,3],[6,3],[1,3],[6,3]],"board":["1 6 1 6 6 6","6 6 1 6 6 1","6 1 6 1 1 6","6 6 2 6 6 6","1 6 6 6 6 6"],"matched_count":27,"matched_main_count":21,"matched_other_count":6,"main_damage_multiplier":16.25,"simulation_times":10000,"combo_count_avg":8.0629,"combo_count_min":5,"main_combo_count_avg":4.9621,"main_damage_multiplier_avg":18.28755625},{"combo_count":7,"main_combo_count":5,"drop_times":4,"combos":[[6,5],[6,3],[6,5],[6,3],[1,4],[6,3],[1,3]],"board":["6 6 6 1 6 6","1 6 2 6 6 6","6 1 6 6 1 6","6 6 6 1 6 1","6 1 1 6 6 6"],"matched_count":26,"matched_main_count":19,"matched_other_count":7,"main_damage_multiplier":15.0,"simulation_times":10000,"combo_count_avg":8.4057,"combo_count_min":7,"main_combo_count_avg":5.3561,"main_damage_multiplier_avg":18.2805125},{"combo_count":7,"main_combo_count":5,"drop_times":4,"combos":[[6,6],[6,3],[6,5],[1,4],[6,3],[1,3],[6,3]],"board":["6 6 1 6 6 6","6 6 2 6 1 6","6 1 6 1 6 6","1 6 6 6 1 1","6 6 1 6 6 6"],"matched_count":27,"matched_main_count":20,"matched_other_count":7,"main_damage_multiplier":15.625,"simulation_times":10000,"combo_count_avg":8.2274,"combo_count_min":5,"main_combo_count_avg":5.1185,"main_damage_multiplier_avg":18.26763125},{"combo_count":7,"main_combo_count":5,"drop_times":5,"combos":[[6,5],[6,3],[6,4],[1,4],[6,3],[1,3],[6,3]],"board":["6 6 6 6 1 6","6 6 1 6 6 1","2 1 6 1 6 6","6 6 6 1 1 6","6 6 1 6 6 6"],"matched_count":25,"matched_main_count":18,"matched_other_count":7,"main_damage_multiplier":14.375,"simulation_times":10000,"combo_count_avg":8.6154,"combo_count_min":6,"main_combo_count_avg":5.4257,"main_damage_multiplier_avg":18.26216875},{"combo_count":7,"main_combo_count":5,"drop_times":4,"combos":[[6,3],[6,4],[6,5],[1,3],[6,3],[6,3],[1,3]],"board":["6 6 1 6 6 6","1 6 6 1 6 6","6 1 6 1 2 6","6 6 1 6 6 1","6 1 6 6 6 6"],"matched_count":24,"matched_main_count":18,"matched_other_count":6,"main_damage_multiplier":14.375,"simulation_times":10000,"combo_count_avg":8.4933,"combo_count_min":7,"main_combo_count_avg":5.5052,"main_damage_multiplier_avg":18.25973125},{"combo_count":7,"main_combo_count":5,"drop_times":4,"combos":[[6,8],[6,3],[6,3],[1,4],[6,3],[1,3],[6,3]],"board":["6 6 1 6 6 6","6 6 2 6 1 1","6 1 6 1 6 6","1 6 6 6 1 6","6 6 1 6 6 6"],"matched_count":27,"matched_main_count":20,"matched_other_count":7,"main_damage_multiplier":15.625,"simulation_times":10000,"combo_count_avg":8.2244,"combo_count_min":6,"main_combo_count_avg":5.1174,"main_damage_multiplier_avg":18.259225},{"combo_count":7,"main_combo_count":5,"drop_times":4,"combos":[[6,9],[6,3],[6,3],[1,3],[6,3],[1,3],[6,3]],"board":["6 6 1 6 6 6","6 6 1 6 6 1","6 1 6 1 1 6","1 6 6 6 6 6","1 6 2 6 6 6"],"matched_count":27,"matched_main_count":21,"matched_other_count":6,"main_damage_multiplier":16.25,"simulation_times":10000,"combo_count_avg":8.0595,"combo_count_min":6,"main_combo_count_avg":4.954,"main_damage_multiplier_avg":18.2518},{"combo_count":7,"main_combo_count":5,"drop_times":4,"combos":[[6,6],[6,3],[6,5],[1,4],[6,3],[1,3],[6,3]],"board":["6 6 1 6 1 6","6 6 2 6 6 6","6 1 6 1 6 6","1 6 6 6 1 1","6 6 1 6 6 6"],"matched_count":27,"matched_main_count":20,"matched_other_count":7,"main_damage_multiplier":15.625,"simulation_times":10000,"combo_count_avg":8.2263,"combo_count_min":5,"main_combo_count_avg":5.1153,"main_damage_multiplier_avg":18.25},{"combo_count":7,"main_combo_count":5,"drop_times":4,"combos":[[6,3],[6,3],[6,3],[6,3],[1,3],[6,4],[1,3]],"board":["6 6 6 1 6 6","6 6 1 6 6 6","1 1 6 6 2 1","6 6 6 1 6 6","6 1 1 6 6 6"],"matched_count":22,"matched_main_count":16,"matched_other_count":6,"main_damage_multiplier":13.125,"simulation_times":10000,"combo_count_avg":8.8944,"combo_count_min":7,"main_combo_count_avg":5.7781,"main_damage_multiplier_avg":18.22198125},{"combo_count":7,"main_combo_count":5,"drop_times":4,"combos":[[6,8],[6,3],[6,3],[1,4],[6,3],[1,3],[6,3]],"board":["6 6 1 6 1 6","6 6 2 1 6 6","6 1 6 6 1 6","1 6 6 6 6 1","6 6 1 6 6 6"],"matched_count":27,"matched_main_count":20,"matched_other_count":7,"main_damage_multiplier":15.625,"simulation_times":10000,"combo_count_avg":8.2228,"combo_count_min":6,"main_combo_count_avg":5.1073,"main_damage_multiplier_avg":18.21035625},{"combo_count":7,"main_combo_count":5,"drop_times":3,"combos":[[6,5],[6,3],[6,5],[6,3],[1,4],[6,3],[1,3]],"board":["6 6 6 1 6 6","1 6 1 6 6 6","6 1 6 6 1 6","6 6 6 1 6 2","6 1 1 6 6 6"],"matched_count":26,"matched_main_count":19,"matched_other_count":7,"main_damage_multiplier":15.0,"simulation_times":10000,"combo_count_avg":8.3864,"combo_count_min":7,"main_combo_count_avg":5.3352,"main_damage_multiplier_avg":18.2075875},{"combo_count":7,"main_combo_count":5,"drop_times":3,"combos":[[6,5],[6,3],[6,5],[6,3],[1,4],[6,3],[1,3]],"board":["6 6 6 1 6 6","1 6 1 6 6 6","6 2 6 6 1 6","6 6 6 1 6 1","6 1 1 6 6 6"],"matched_count":26,"matched_main_count":19,"matched_other_count":7,"main_damage_multiplier":15.0,"simulation_times":10000,"combo_count_avg":8.3999,"combo_count_min":7,"main_combo_count_avg":5.3275,"main_damage_multiplier_avg":18.201825},{"combo_count":7,"main_combo_count":5,"drop_times":4,"combos":[[6,9],[6,3],[6,3],[1,3],[6,3],[1,3],[6,3]],"board":["6 6 1 6 6 6","6 6 1 6 6 1","6 1 6 1 1 6","1 6 2 6 6 6","1 6 6 6 6 6"],"matched_count":27,"matched_main_count":21,"matched_other_count":6,"main_damage_multiplier":16.25,"simulation_times":10000,"combo_count_avg":8.037,"combo_count_min":6,"main_combo_count_avg":4.9481,"main_damage_multiplier_avg":18.2018},{"combo_count":7,"main_combo_count":5,"drop_times":3,"combos":[[6,3],[6,4],[6,5],[6,3],[1,3],[1,3],[6,4]],"board":["6 6 6 1 6 6","1 6 1 6 6 6","6 1 6 1 2 6","6 6 1 6 6 1","6 1 6 6 6 6"],"matched_count":25,"matched_main_count":19,"matched_other_count":6,"main_damage_multiplier":15.0,"simulation_times":10000,"combo_count_avg":8.2567,"combo_count_min":6,"main_combo_count_avg":5.3256,"main_damage_multiplier_avg":18.19016875},{"combo_count":7,"main_combo_count":5,"drop_times":3,"combos":[[6,5],[6,3],[6,5],[6,3],[1,3],[6,3],[1,3]],"board":["6 6 6 1 6 6","1 6 1 6 6 6","6 1 6 6 1 6","6 6 6 1 1 2","6 6 1 6 6 6"],"matched_count":25,"matched_main_count":19,"matched_other_count":6,"main_damage_multiplier":15.0,"simulation_times":10000,"combo_count_avg":8.389,"combo_count_min":7,"main_combo_count_avg":5.328,"main_damage_multiplier_avg":18.17553125},{"combo_count":7,"main_combo_count":5,"drop_times":3,"combos":[[6,5],[6,3],[6,5],[6,3],[1,3],[6,3],[1,3]],"board":["6 6 6 1 6 6","2 6 1 6 6 6","6 1 6 6 1 6","6 6 6 1 6 1","6 1 1 6 6 6"],"matched_count":25,"matched_main_count":19,"matched_other_count":6,"main_damage_multiplier":15.0,"simulation_times":10000,"combo_count_avg":8.3772,"combo_count_min":7,"main_combo_count_avg":5.3329,"main_damage_multiplier_avg":18.1739625},{"combo_count":7,"main_combo_count":5,"drop_times":3,"combos":[[6,5],[6,3],[6,3],[6,3],[1,3],[6,4],[1,4]],"board":["6 6 6 1 6 6","2 6 1 6 6 6","6 1 6 6 1 1","6 6 6 1 6 6","6 1 1 6 6 6"],"matched_count":25,"matched_main_count":18,"matched_other_count":7,"main_damage_multiplier":14.375,"simulation_times":10000,"combo_count_avg":8.4996,"combo_count_min":7,"main_combo_count_avg":5.4786,"main_damage_multiplier_avg":18.1316375},{"combo_count":7,"main_combo_count":5,"drop_times":3,"combos":[[6,3],[6,3],[6,5],[6,3],[1,3],[6,4],[1,4]],"board":["6 6 6 1 6 6","6 6 1 6 6 6","1 1 6 6 1 6","6 6 6 1 1 2","6 6 1 6 6 6"],"matched_count":25,"matched_main_count":18,"matched_other_count":7,"main_damage_multiplier":14.375,"simulation_times":10000,"combo_count_avg":8.5043,"combo_count_min":7,"main_combo_count_avg":5.4752,"main_damage_multiplier_avg":18.122275},{"combo_count":7,"main_combo_count":5,"drop_times":3,"combos":[[6,3],[6,4],[6,5],[6,3],[1,3],[1,3],[6,4]],"board":["6 6 6 1 6 6","1 6 1 6 6 6","6 1 6 2 1 6","6 6 1 6 6 1","6 1 6 6 6 6"],"matched_count":25,"matched_main_count":19,"matched_other_count":6,"main_damage_multiplier":15.0,"simulation_times":10000,"combo_count_avg":8.2394,"combo_count_min":6,"main_combo_count_avg":5.3116,"main_damage_multiplier_avg":18.091},{"combo_count":7,"main_combo_count":5,"drop_times":3,"combos":[[6,5],[6,3],[6,3],[6,3],[1,4],[6,4],[1,4]],"board":["6 6 6 1 6 6","1 6 1 6 6 6","6 2 6 6 1 1","6 6 6 1 6 6","6 1 1 6 6 6"],"matched_count":26,"matched_main_count":18,"matched_other_count":8,"main_damage_multiplier":14.375,"simulation_times":10000,"combo_count_avg":8.489,"combo_count_min":7,"main_combo_count_avg":5.4685,"main_damage_multiplier_avg":18.0757375},{"combo_count":7,"main_combo_count":5,"drop_times":4,"combos":[[6,3],[6,3],[6,5],[6,3],[1,3],[6,3],[1,3]],"board":["6 6 6 1 6 6","6 6 1 6 6 6","1 1 6 6 2 6","6 6 6 1 6 1","6 1 1 6 6 6"],"matched_count":23,"matched_main_count":17,"matched_other_count":6,"main_damage_multiplier":13.75,"simulation_times":10000,"combo_count_avg":8.7332,"combo_count_min":7,"main_combo_count_avg":5.5793,"main_damage_multiplier_avg":18.07224375},{"combo_count":7,"main_combo_count":5,"drop_times":4,"combos":[[6,3],[6,4],[6,5],[1,3],[6,3],[6,3],[1,3]],"board":["6 6 2 6 6 6","1 6 6 1 6 6","6 1 6 1 1 6","6 6 1 6 6 1","6 1 6 6 6 6"],"matched_count":24,"matched_main_count":18,"matched_other_count":6,"main_damage_multiplier":14.375,"simulation_times":10000,"combo_count_avg":8.3861,"combo_count_min":7,"main_combo_count_avg":5.4756,"main_damage_multiplier_avg":18.0444125},{"combo_count":7,"main_combo_count":5,"drop_times":4,"combos":[[6,7],[6,3],[6,3],[1,4],[6,4],[1,3],[6,3]],"board":["6 6 1 6 6 1","6 6 2 6 6 6","6 1 6 1 1 6","1 6 6 6 6 1","6 6 1 6 6 6"],"matched_count":27,"matched_main_count":20,"matched_other_count":7,"main_damage_multiplier":15.625,"simulation_times":10000,"combo_count_avg":8.1816,"combo_count_min":6,"main_combo_count_avg":5.0915,"main_damage_multiplier_avg":18.03294375},{"combo_count":7,"main_combo_count":5,"drop_times":3,"combos":[[6,5],[6,3],[6,3],[6,3],[1,4],[6,4],[1,3]],"board":["6 6 6 1 6 6","1 6 2 6 6 6","6 1 6 6 1 1","6 6 6 1 6 6","6 1 1 6 6 6"],"matched_count":25,"matched_main_count":18,"matched_other_count":7,"main_damage_multiplier":14.375,"simulation_times":10000,"combo_count_avg":8.4488,"combo_count_min":7,"main_combo_count_avg":5.4695,"main_damage_multiplier_avg":18.01808125},{"combo_count":7,"main_combo_count":5,"drop_times":4,"combos":[[6,5],[6,3],[6,3],[6,3],[1,3],[6,3],[1,3]],"board":["6 6 6 1 6 6","1 6 1 6 6 6","6 2 6 6 1 1","6 6 6 1 1 6","6 6 1 6 6 6"],"matched_count":23,"matched_main_count":17,"matched_other_count":6,"main_damage_multiplier":13.75,"simulation_times":10000,"combo_count_avg":8.7186,"combo_count_min":7,"main_combo_count_avg":5.5617,"main_damage_multiplier_avg":17.9927},{"combo_count":7,"main_combo_count":5,"drop_times":3,"combos":[[6,5],[6,3],[6,3],[6,3],[1,4],[6,4],[1,3]],"board":["6 6 6 1 6 6","1 6 1 6 6 6","6 1 6 6 1 2","6 6 6 1 6 6","6 1 1 6 6 6"],"matched_count":25,"matched_main_count":18,"matched_other_count":7,"main_damage_multiplier":14.375,"simulation_times":10000,"combo_count_avg":8.4348,"combo_count_min":7,"main_combo_count_avg":5.4684,"main_damage_multiplier_avg":17.98275625},{"combo_count":7,"main_combo_count":5,"drop_times":3,"combos":[[6,3],[6,6],[6,3],[6,3],[1,4],[6,3],[1,3]],"board":["6 6 6 1 6 6","1 6 1 6 6 6","6 2 6 6 1 1","6 1 6 1 6 6","6 1 6 6 6 6"],"matched_count":25,"matched_main_count":18,"matched_other_count":7,"main_damage_multiplier":14.375,"simulation_times":10000,"combo_count_avg":8.3899,"combo_count_min":6,"main_combo_count_avg":5.4488,"main_damage_multiplier_avg":17.96436875},{"combo_count":7,"main_combo_count":5,"drop_times":4,"combos":[[6,7],[6,3],[6,3],[1,4],[6,4],[1,3],[6,3]],"board":["6 6 1 6 6 6","6 6 2 6 6 1","6 1 6 1 1 6","1 6 6 6 6 1","6 6 1 6 6 6"],"matched_count":27,"matched_main_count":20,"matched_other_count":7,"main_damage_multiplier":15.625,"simulation_times":10000,"combo_count_avg":8.145,"combo_count_min":6,"main_combo_count_avg":5.0833,"main_damage_multiplier_avg":17.9506375},{"combo_count":7,"main_combo_count":5,"drop_times":3,"combos":[[6,3],[6,6],[6,3],[6,3],[1,4],[6,3],[1,3]],"board":["6 6 6 1 6 6","1 6 1 6 6 6","6 1 6 6 1 1","6 2 6 1 6 6","6 1 6 6 6 6"],"matched_count":25,"matched_main_count":18,"matched_other_count":7,"main_damage_multiplier":14.375,"simulation_times":10000,"combo_count_avg":8.3603,"combo_count_min":6,"main_combo_count_avg":5.4504,"main_damage_multiplier_avg":17.947825},{"combo_count":7,"main_combo_count":5,"drop_times":4,"combos":[[6,8],[6,3],[6,3],[1,4],[6,3],[1,3],[6,3]],"board":["6 6 1 6 2 6","6 6 1 1 6 6","6 1 6 6 1 6","1 6 6 6 6 1","6 6 1 6 6 6"],"matched_count":27,"matched_main_count":20,"matched_other_count":7,"main_damage_multiplier":15.625,"simulation_times":10000,"combo_count_avg":8.1313,"combo_count_min":5,"main_combo_count_avg":5.0387,"main_damage_multiplier_avg":17.9168875},{"combo_count":7,"main_combo_count":5,"drop_times":4,"combos":[[6,3],[6,5],[6,3],[1,3],[6,3],[6,3],[1,3]],"board":["6 6 6 1 6 6","6 6 1 6 6 6","6 2 6 6 1 1","1 6 6 1 1 6","6 6 1 6 6 6"],"matched_count":23,"matched_main_count":17,"matched_other_count":6,"main_damage_multiplier":13.75,"simulation_times":10000,"combo_count_avg":8.6348,"combo_count_min":7,"main_combo_count_avg":5.5624,"main_damage_multiplier_avg":17.89681875},{"combo_count":7,"main_combo_count":5,"drop_times":4,"combos":[[6,6],[6,3],[6,5],[1,3],[6,3],[1,3],[6,3]],"board":["6 6 1 6 6 6","6 6 1 6 1 6","6 1 6 1 6 6","1 6 6 6 1 1","6 6 2 6 6 6"],"matched_count":26,"matched_main_count":20,"matched_other_count":6,"main_damage_multiplier":15.625,"simulation_times":10000,"combo_count_avg":8.1544,"combo_count_min":6,"main_combo_count_avg":5.0289,"main_damage_multiplier_avg":17.89028125},{"combo_count":7,"main_combo_count":5,"drop_times":4,"combos":[[6,6],[6,3],[6,5],[1,3],[6,3],[1,3],[6,3]],"board":["6 6 1 6 1 6","6 6 1 6 6 6","6 1 6 1 6 6","1 6 6 6 1 1","6 6 2 6 6 6"],"matched_count":26,"matched_main_count":20,"matched_other_count":6,"main_damage_multiplier":15.625,"simulation_times":10000,"combo_count_avg":8.157,"combo_count_min":5,"main_combo_count_avg":5.0227,"main_damage_multiplier_avg":17.88866875},{"combo_count":7,"main_combo_count":5,"drop_times":4,"combos":[[6,6],[6,3],[6,5],[1,4],[6,3],[1,3],[6,3]],"board":["6 6 1 6 6 6","6 6 1 6 2 6","6 1 6 1 6 6","1 6 6 6 1 1","6 6 1 6 6 6"],"matched_count":27,"matched_main_count":20,"matched_other_count":7,"main_damage_multiplier":15.625,"simulation_times":10000,"combo_count_avg":8.1103,"combo_count_min":5,"main_combo_count_avg":5.0436,"main_damage_multiplier_avg":17.88445},{"combo_count":7,"main_combo_count":5,"drop_times":4,"combos":[[6,8],[6,3],[6,3],[1,4],[6,3],[1,3],[6,3]],"board":["6 6 1 6 6 6","6 6 1 6 2 1","6 1 6 1 6 6","1 6 6 6 1 6","6 6 1 6 6 6"],"matched_count":27,"matched_main_count":20,"matched_other_count":7,"main_damage_multiplier":15.625,"simulation_times":10000,"combo_count_avg":8.1197,"combo_count_min":6,"main_combo_count_avg":5.0374,"main_damage_multiplier_avg":17.88441875},{"combo_count":7,"main_combo_count":5,"drop_times":3,"combos":[[6,3],[6,4],[6,5],[1,3],[6,3],[6,3],[1,3]],"board":["6 6 1 6 6 6","1 6 6 2 6 6","6 1 6 1 1 6","6 6 1 6 6 1","6 1 6 6 6 6"],"matched_count":24,"matched_main_count":18,"matched_other_count":6,"main_damage_multiplier":14.375,"simulation_times":10000,"combo_count_avg":8.3459,"combo_count_min":7,"main_combo_count_avg":5.45,"main_damage_multiplier_avg":17.87736875},{"combo_count":7,"main_combo_count":5,"drop_times":4,"combos":[[6,8],[6,3],[6,3],[1,3],[6,3],[1,3],[6,3]],"board":["6 6 1 6 1 6","6 6 1 1 6 6","6 1 6 6 1 6","1 6 6 6 6 1","6 6 2 6 6 6"],"matched_count":26,"matched_main_count":20,"matched_other_count":6,"main_damage_multiplier":15.625,"simulation_times":10000,"combo_count_avg":8.1551,"combo_count_min":5,"main_combo_count_avg":5.0223,"main_damage_multiplier_avg":17.87456875},{"combo_count":7,"main_combo_count":5,"drop_times":4,"combos":[[6,6],[6,3],[6,5],[1,4],[6,3],[1,3],[6,3]],"board":["6 6 1 6 2 6","6 6 1 6 6 6","6 1 6 1 6 6","1 6 6 6 1 1","6 6 1 6 6 6"],"matched_count":27,"matched_main_count":20,"matched_other_count":7,"main_damage_multiplier":15.625,"simulation_times":10000,"combo_count_avg":8.1104,"combo_count_min":6,"main_combo_count_avg":5.0334,"main_damage_multiplier_avg":17.85785},{"combo_count":7,"main_combo_count":5,"drop_times":3,"combos":[[6,3],[6,4],[6,5],[6,3],[1,3],[1,3],[6,3]],"board":["6 6 6 1 6 6","1 6 1 6 6 6","6 1 6 1 6 2","6 6 1 6 1 6","6 1 6 6 6 6"],"matched_count":24,"matched_main_count":18,"matched_other_count":6,"main_damage_multiplier":14.375,"simulation_times":10000,"combo_count_avg":8.4149,"combo_count_min":6,"main_combo_count_avg":5.3319,"main_damage_multiplier_avg":17.83734375},{"combo_count":7,"main_combo_count":5,"drop_times":4,"combos":[[6,8],[6,3],[6,3],[1,3],[6,3],[1,3],[6,3]],"board":["6 6 1 6 6 6","6 6 1 6 1 1","6 1 6 1 6 6","1 6 6 6 1 6","6 6 2 6 6 6"],"matched_count":26,"matched_main_count":20,"matched_other_count":6,"main_damage_multiplier":15.625,"simulation_times":10000,"combo_count_avg":8.1284,"combo_count_min":5,"main_combo_count_avg":5.0118,"main_damage_multiplier_avg":17.8039},{"combo_count":7,"main_combo_count":5,"drop_times":3,"combos":[[6,3],[6,4],[6,5],[1,3],[6,3],[6,3],[1,3]],"board":["6 6 1 6 6 6","1 6 6 1 6 6","6 2 6 1 1 6","6 6 1 6 6 1","6 1 6 6 6 6"],"matched_count":24,"matched_main_count":18,"matched_other_count":6,"main_damage_multiplier":14.375,"simulation_times":10000,"combo_count_avg":8.2845,"combo_count_min":7,"main_combo_count_avg":5.4396,"main_damage_multiplier_avg":17.77308125},{"combo_count":7,"main_combo_count":5,"drop_times":3,"combos":[[6,3],[6,4],[6,5],[6,3],[1,3],[1,3],[6,3]],"board":["6 6 6 1 6 6","1 6 1 6 6 6","6 1 6 1 6 1","6 6 1 6 2 6","6 1 6 6 6 6"],"matched_count":24,"matched_main_count":18,"matched_other_count":6,"main_damage_multiplier":14.375,"simulation_times":10000,"combo_count_avg":8.3265,"combo_count_min":6,"main_combo_count_avg":5.337,"main_damage_multiplier_avg":17.7336625},{"combo_count":7,"main_combo_count":5,"drop_times":4,"combos":[[6,8],[6,3],[6,3],[1,3],[6,3],[1,3],[6,3]],"board":["6 6 1 6 6 6","6 6 1 6 6 1","6 1 6 1 1 2","1 6 6 6 6 6","6 6 1 6 6 6"],"matched_count":26,"matched_main_count":20,"matched_other_count":6,"main_damage_multiplier":15.625,"simulation_times":10000,"combo_count_avg":8.0824,"combo_count_min":6,"main_combo_count_avg":5.0215,"main_damage_multiplier_avg":17.7087375},{"combo_count":7,"main_combo_count":5,"drop_times":4,"combos":[[6,3],[6,4],[6,5],[6,3],[1,3],[6,3],[1,3]],"board":["6 6 6 1 6 6","1 6 1 6 6 6","6 2 6 1 6 1","6 6 1 6 1 6","6 1 6 6 6 6"],"matched_count":24,"matched_main_count":18,"matched_other_count":6,"main_damage_multiplier":14.375,"simulation_times":10000,"combo_count_avg":8.37,"combo_count_min":6,"main_combo_count_avg":5.3962,"main_damage_multiplier_avg":17.69980625},{"combo_count":7,"main_combo_count":5,"drop_times":3,"combos":[[6,3],[6,4],[6,5],[6,3],[1,3],[6,4],[1,4]],"board":["6 6 6 2 6 6","1 6 1 6 6 6","6 1 6 1 1 6","6 6 1 6 6 1","6 1 6 6 6 6"],"matched_count":26,"matched_main_count":19,"matched_other_count":7,"main_damage_multiplier":15.0,"simulation_times":10000,"combo_count_avg":8.2211,"combo_count_min":6,"main_combo_count_avg":5.2609,"main_damage_multiplier_avg":17.67939375},{"combo_count":7,"main_combo_count":5,"drop_times":4,"combos":[[6,7],[6,3],[6,3],[1,4],[6,4],[1,3],[6,3]],"board":["6 6 1 6 6 6","6 6 1 6 6 2","6 1 6 1 1 6","1 6 6 6 6 1","6 6 1 6 6 6"],"matched_count":27,"matched_main_count":20,"matched_other_count":7,"main_damage_multiplier":15.625,"simulation_times":10000,"combo_count_avg":8.0701,"combo_count_min":6,"main_combo_count_avg":5.0182,"main_damage_multiplier_avg":17.67281875},{"combo_count":7,"main_combo_count":5,"drop_times":5,"combos":[[6,3],[6,4],[6,6],[1,3],[6,3],[1,3],[6,3]],"board":["6 6 6 6 6 6","1 6 1 6 1 6","6 2 6 1 6 1","6 6 1 6 1 6","6 1 6 6 6 6"],"matched_count":25,"matched_main_count":19,"matched_other_count":6,"main_damage_multiplier":15.0,"simulation_times":10000,"combo_count_avg":8.2535,"combo_count_min":5,"main_combo_count_avg":5.1532,"main_damage_multiplier_avg":17.67186875},{"combo_count":7,"main_combo_count":5,"drop_times":4,"combos":[[6,3],[6,4],[6,6],[1,3],[6,4],[1,3],[6,3]],"board":["6 6 6 6 6 6","1 6 2 6 6 1","6 1 6 1 1 6","6 6 1 6 6 1","6 1 6 6 6 6"],"matched_count":26,"matched_main_count":20,"matched_other_count":6,"main_damage_multiplier":15.625,"simulation_times":10000,"combo_count_avg":7.979,"combo_count_min":5,"main_combo_count_avg":5.1106,"main_damage_multiplier_avg":17.66765625},{"combo_count":7,"main_combo_count":5,"drop_times":4,"combos":[[6,8],[6,3],[6,3],[1,3],[6,3],[1,3],[6,3]],"board":["6 6 1 6 6 1","6 6 1 6 6 6","6 1 6 1 1 2","1 6 6 6 6 6","6 6 1 6 6 6"],"matched_count":26,"matched_main_count":20,"matched_other_count":6,"main_damage_multiplier":15.625,"simulation_times":10000,"combo_count_avg":8.0562,"combo_count_min":6,"main_combo_count_avg":5.0202,"main_damage_multiplier_avg":17.66553125},{"combo_count":7,"main_combo_count":5,"drop_times":4,"combos":[[6,4],[6,4],[6,5],[1,3],[6,4],[1,3],[6,3]],"board":["1 6 6 6 6 6","6 6 2 6 6 1","6 1 6 1 1 6","6 6 1 6 6 1","6 1 6 6 6 6"],"matched_count":26,"matched_main_count":20,"matched_other_count":6,"main_damage_multiplier":15.625,"simulation_times":10000,"combo_count_avg":7.9692,"combo_count_min":5,"main_combo_count_avg":5.1072,"main_damage_multiplier_avg":17.6547875},{"combo_count":7,"main_combo_count":5,"drop_times":4,"combos":[[6,8],[6,3],[6,3],[1,3],[6,3],[6,3],[1,3]],"board":["6 1 6 6 1 6","6 6 6 1 6 6","6 6 2 6 1 6","1 6 6 1 6 1","6 6 1 6 6 6"],"matched_count":26,"matched_main_count":20,"matched_other_count":6,"main_damage_multiplier":15.625,"simulation_times":10000,"combo_count_avg":8.0038,"combo_count_min":5,"main_combo_count_avg":5.0272,"main_damage_multiplier_avg":17.6520875},{"combo_count":7,"main_combo_count":5,"drop_times":5,"combos":[[6,4],[6,6],[6,3],[1,3],[6,3],[1,3],[6,3]],"board":["6 6 1 6 6 6","6 2 6 6 1 6","6 6 6 1 6 1","6 6 1 6 1 6","1 1 6 6 6 6"],"matched_count":25,"matched_main_count":19,"matched_other_count":6,"main_damage_multiplier":15.0,"simulation_times":10000,"combo_count_avg":8.2494,"combo_count_min":5,"main_combo_count_avg":5.1536,"main_damage_multiplier_avg":17.6423125},{"combo_count":7,"main_combo_count":5,"drop_times":5,"combos":[[6,6],[6,4],[6,3],[1,3],[6,3],[1,3],[6,3]],"board":["1 6 1 6 6 6","6 2 6 6 1 6","6 6 6 1 6 1","6 6 1 6 1 6","6 1 6 6 6 6"],"matched_count":25,"matched_main_count":19,"matched_other_count":6,"main_damage_multiplier":15.0,"simulation_times":10000,"combo_count_avg":8.2321,"combo_count_min":5,"main_combo_count_avg":5.1555,"main_damage_multiplier_avg":17.6330625},{"combo_count":7,"main_combo_count":5,"drop_times":4,"combos":[[6,7],[6,3],[6,3],[1,3],[6,3],[1,3],[6,3]],"board":["6 6 6 1 6 6","6 6 1 2 6 6","6 1 6 1 1 6","6 6 1 6 6 1","6 6 1 6 6 6"],"matched_count":25,"matched_main_count":19,"matched_other_count":6,"main_damage_multiplier":15.0,"simulation_times":10000,"combo_count_avg":8.1687,"combo_count_min":7,"main_combo_count_avg":5.1988,"main_damage_multiplier_avg":17.62841875},{"combo_count":7,"main_combo_count":5,"drop_times":3,"combos":[[6,5],[6,3],[6,4],[1,3],[6,3],[1,3],[6,3]],"board":["6 6 6 6 1 6","6 6 1 6 6 2","1 1 6 1 6 6","6 6 6 1 1 6","6 6 1 6 6 6"],"matched_count":24,"matched_main_count":18,"matched_other_count":6,"main_damage_multiplier":14.375,"simulation_times":10000,"combo_count_avg":8.3581,"combo_count_min":6,"main_combo_count_avg":5.353,"main_damage_multiplier_avg":17.61740625},{"combo_count":7,"main_combo_count":5,"drop_times":4,"combos":[[6,7],[6,3],[6,3],[1,3],[6,4],[1,3],[6,3]],"board":["6 6 1 6 6 1","6 6 1 6 6 6","6 1 6 1 1 6","1 6 6 6 6 1","6 6 2 6 6 6"],"matched_count":26,"matched_main_count":20,"matched_other_count":6,"main_damage_multiplier":15.625,"simulation_times":10000,"combo_count_avg":8.0424,"combo_count_min":6,"main_combo_count_avg":5.0193,"main_damage_multiplier_avg":17.6046625},{"combo_count":7,"main_combo_count":5,"drop_times":4,"combos":[[6,7],[6,3],[6,3],[1,3],[6,4],[1,3],[6,3]],"board":["6 6 1 6 6 1","6 6 1 6 6 6","6 1 6 1 1 6","1 6 6 6 6 2","6 6 1 6 6 6"],"matched_count":26,"matched_main_count":20,"matched_other_count":6,"main_damage_multiplier":15.625,"simulation_times":10000,"combo_count_avg":8.0405,"combo_count_min":6,"main_combo_count_avg":5.004,"main_damage_multiplier_avg":17.597475},{"combo_count":7,"main_combo_count":5,"drop_times":5,"combos":[[6,4],[6,4],[6,5],[1,3],[6,3],[1,3],[6,3]],"board":["1 6 6 6 6 6","6 6 1 6 1 6","6 2 6 1 6 1","6 6 1 6 1 6","6 1 6 6 6 6"],"matched_count":25,"matched_main_count":19,"matched_other_count":6,"main_damage_multiplier":15.0,"simulation_times":10000,"combo_count_avg":8.2159,"combo_count_min":5,"main_combo_count_avg":5.1438,"main_damage_multiplier_avg":17.57796875},{"combo_count":7,"main_combo_count":5,"drop_times":4,"combos":[[6,3],[6,6],[6,4],[1,3],[6,3],[1,4],[6,3]],"board":["6 6 6 6 1 6","1 6 1 6 6 1","6 2 6 1 6 6","6 6 1 6 1 6","6 1 6 6 6 6"],"matched_count":26,"matched_main_count":19,"matched_other_count":7,"main_damage_multiplier":15.0,"simulation_times":10000,"combo_count_avg":8.1198,"combo_count_min":5,"main_combo_count_avg":5.1697,"main_damage_multiplier_avg":17.56623125},{"combo_count":7,"main_combo_count":5,"drop_times":4,"combos":[[6,7],[6,3],[6,3],[1,3],[6,4],[1,3],[6,3]],"board":["6 6 1 6 6 6","6 6 1 6 6 1","6 1 6 1 1 6","1 6 6 6 6 2","6 6 1 6 6 6"],"matched_count":26,"matched_main_count":20,"matched_other_count":6,"main_damage_multiplier":15.625,"simulation_times":10000,"combo_count_avg":8.0194,"combo_count_min":6,"main_combo_count_avg":5.0085,"main_damage_multiplier_avg":17.5648},{"combo_count":7,"main_combo_count":5,"drop_times":4,"combos":[[6,3],[6,5],[6,3],[1,3],[6,3],[6,3],[1,4]],"board":["6 6 6 1 6 6","6 6 1 6 6 6","6 1 6 6 1 1","2 6 6 1 1 6","6 6 1 6 6 6"],"matched_count":24,"matched_main_count":17,"matched_other_count":7,"main_damage_multiplier":13.75,"simulation_times":10000,"combo_count_avg":8.5315,"combo_count_min":7,"main_combo_count_avg":5.5141,"main_damage_multiplier_avg":17.564675},{"combo_count":7,"main_combo_count":5,"drop_times":4,"combos":[[6,7],[6,3],[6,3],[1,3],[6,3],[1,3],[6,3]],"board":["6 6 1 1 6 6","6 6 6 2 6 6","6 1 6 1 1 6","6 6 1 6 6 1","6 6 1 6 6 6"],"matched_count":25,"matched_main_count":19,"matched_other_count":6,"main_damage_multiplier":15.0,"simulation_times":10000,"combo_count_avg":8.1364,"combo_count_min":7,"main_combo_count_avg":5.1947,"main_damage_multiplier_avg":17.562975},{"combo_count":7,"main_combo_count":5,"drop_times":4,"combos":[[6,7],[6,3],[6,3],[1,4],[6,4],[1,3],[6,3]],"board":["6 6 1 6 6 2","6 6 1 6 6 6","6 1 6 1 1 6","1 6 6 6 6 1","6 6 1 6 6 6"],"matched_count":27,"matched_main_count":20,"matched_other_count":7,"main_damage_multiplier":15.625,"simulation_times":10000,"combo_count_avg":8.024,"combo_count_min":6,"main_combo_count_avg":5.0049,"main_damage_multiplier_avg":17.5624},{"combo_count":7,"main_combo_count":5,"drop_times":4,"combos":[[6,7],[6,3],[6,3],[1,3],[6,4],[1,3],[6,3]],"board":["6 6 1 6 6 6","6 6 1 6 6 1","6 1 6 1 1 6","1 6 6 6 6 1","6 6 2 6 6 6"],"matched_count":26,"matched_main_count":20,"matched_other_count":6,"main_damage_multiplier":15.625,"simulation_times":10000,"combo_count_avg":8.0074,"combo_count_min":6,"main_combo_count_avg":5.0182,"main_damage_multiplier_avg":17.53693125},{"combo_count":7,"main_combo_count":5,"drop_times":4,"combos":[[6,4],[6,6],[6,3],[1,3],[6,3],[1,4],[6,3]],"board":["1 6 6 6 1 6","6 6 1 6 6 1","6 2 6 1 6 6","6 6 1 6 1 6","6 1 6 6 6 6"],"matched_count":26,"matched_main_count":19,"matched_other_count":7,"main_damage_multiplier":15.0,"simulation_times":10000,"combo_count_avg":8.1064,"combo_count_min":5,"main_combo_count_avg":5.1646,"main_damage_multiplier_avg":17.53039375},{"combo_count":7,"main_combo_count":5,"drop_times":3,"combos":[[6,3],[6,4],[6,5],[6,3],[1,3],[1,3],[6,3]],"board":["6 6 6 1 6 6","1 6 1 6 6 6","6 1 6 2 6 1","6 6 1 6 1 6","6 1 6 6 6 6"],"matched_count":24,"matched_main_count":18,"matched_other_count":6,"main_damage_multiplier":14.375,"simulation_times":10000,"combo_count_avg":8.2836,"combo_count_min":6,"main_combo_count_avg":5.3,"main_damage_multiplier_avg":17.50944375},{"combo_count":7,"main_combo_count":5,"drop_times":3,"combos":[[6,3],[6,4],[6,5],[6,3],[1,3],[6,4],[1,3]],"board":["6 6 6 1 6 6","1 6 1 6 6 6","6 2 6 1 1 6","6 6 1 6 6 1","6 1 6 6 6 6"],"matched_count":25,"matched_main_count":19,"matched_other_count":6,"main_damage_multiplier":15.0,"simulation_times":10000,"combo_count_avg":8.0586,"combo_count_min":6,"main_combo_count_avg":5.2962,"main_damage_multiplier_avg":17.4984125},{"combo_count":7,"main_combo_count":5,"drop_times":4,"combos":[[6,3],[6,4],[6,5],[6,3],[1,3],[6,4],[1,3]],"board":["6 6 6 1 6 6","1 6 2 6 6 6","6 1 6 1 1 6","6 6 1 6 6 1","6 1 6 6 6 6"],"matched_count":25,"matched_main_count":19,"matched_other_count":6,"main_damage_multiplier":15.0,"simulation_times":10000,"combo_count_avg":8.0215,"combo_count_min":6,"main_combo_count_avg":5.2878,"main_damage_multiplier_avg":17.4108625},{"combo_count":7,"main_combo_count":5,"drop_times":2,"combos":[[6,3],[6,4],[6,3],[6,3],[1,3],[6,3],[1,3]],"board":["6 6 6 1 6 6","2 6 1 6 6 6","6 1 6 6 1 1","6 6 1 1 6 6","6 1 6 6 6 6"],"matched_count":22,"matched_main_count":16,"matched_other_count":6,"main_damage_multiplier":13.125,"simulation_times":10000,"combo_count_avg":8.577,"combo_count_min":7,"main_combo_count_avg":5.6033,"main_damage_multiplier_avg":17.35433125},{"combo_count":7,"main_combo_count":5,"drop_times":3,"combos":[[6,5],[6,3],[6,3],[6,3],[1,3],[6,3],[1,4]],"board":["6 6 6 1 6 6","6 1 1 6 6 6","1 6 2 6 1 1","6 6 6 1 6 6","6 6 1 6 6 6"],"matched_count":24,"matched_main_count":17,"matched_other_count":7,"main_damage_multiplier":13.75,"simulation_times":10000,"combo_count_avg":8.4705,"combo_count_min":6,"main_combo_count_avg":5.4714,"main_damage_multiplier_avg":17.34901875},{"combo_count":7,"main_combo_count":5,"drop_times":3,"combos":[[6,3],[6,3],[6,5],[6,3],[1,3],[6,3],[1,4]],"board":["6 6 6 1 6 6","6 6 1 6 6 6","1 1 6 2 6 1","6 6 6 1 1 6","6 6 1 6 6 6"],"matched_count":24,"matched_main_count":17,"matched_other_count":7,"main_damage_multiplier":13.75,"simulation_times":10000,"combo_count_avg":8.4644,"combo_count_min":6,"main_combo_count_avg":5.4667,"main_damage_multiplier_avg":17.322675},{"combo_count":7,"main_combo_count":5,"drop_times":3,"combos":[[6,3],[6,3],[6,5],[6,3],[1,5],[6,3],[1,3]],"board":["6 6 6 1 6 6","6 6 1 6 6 6","1 1 6 1 6 2","6 6 6 1 1 6","6 6 1 6 6 6"],"matched_count":25,"matched_main_count":17,"matched_other_count":8,"main_damage_multiplier":13.75,"simulation_times":10000,"combo_count_avg":8.3417,"combo_count_min":6,"main_combo_count_avg":5.4586,"main_damage_multiplier_avg":17.31649375},{"combo_count":7,"main_combo_count":5,"drop_times":3,"combos":[[6,8],[6,3],[6,3],[1,3],[6,3],[1,3],[6,3]],"board":["6 1 6 6 1 6","6 6 6 1 6 6","6 6 1 6 1 6","2 6 6 1 6 1","6 6 1 6 6 6"],"matched_count":26,"matched_main_count":20,"matched_other_count":6,"main_damage_multiplier":15.625,"simulation_times":10000,"combo_count_avg":7.9149,"combo_count_min":5,"main_combo_count_avg":4.9307,"main_damage_multiplier_avg":17.30431875},{"combo_count":7,"main_combo_count":5,"drop_times":4,"combos":[[6,6],[6,3],[6,5],[1,3],[6,3],[1,3],[6,3]],"board":["6 6 1 6 1 6","6 6 1 6 6 6","6 1 6 1 6 6","1 6 6 6 1 2","6 6 1 6 6 6"],"matched_count":26,"matched_main_count":20,"matched_other_count":6,"main_damage_multiplier":15.625,"simulation_times":10000,"combo_count_avg":7.9252,"combo_count_min":6,"main_combo_count_avg":4.932,"main_damage_multiplier_avg":17.3008125},{"combo_count":7,"main_combo_count":5,"drop_times":3,"combos":[[6,5],[6,3],[6,3],[1,3],[6,3],[6,3],[1,3]],"board":["6 6 6 1 6 6","6 6 1 1 6 6","1 1 6 6 1 6","6 6 1 6 6 2","6 6 1 6 6 6"],"matched_count":23,"matched_main_count":17,"matched_other_count":6,"main_damage_multiplier":13.75,"simulation_times":10000,"combo_count_avg":8.3024,"combo_count_min":5,"main_combo_count_avg":5.3857,"main_damage_multiplier_avg":17.28953125},{"combo_count":7,"main_combo_count":5,"drop_times":4,"combos":[[6,8],[6,3],[6,3],[1,3],[6,3],[1,3],[6,3]],"board":["6 6 1 6 6 6","6 6 1 6 1 2","6 1 6 1 6 6","1 6 6 6 1 6","6 6 1 6 6 6"],"matched_count":26,"matched_main_count":20,"matched_other_count":6,"main_damage_multiplier":15.625,"simulation_times":10000,"combo_count_avg":7.917,"combo_count_min":6,"main_combo_count_avg":4.9258,"main_damage_multiplier_avg":17.25985625},{"combo_count":7,"main_combo_count":5,"drop_times":4,"combos":[[6,6],[6,3],[6,5],[1,3],[6,3],[1,3],[6,3]],"board":["6 6 1 6 6 6","6 6 1 6 1 6","6 1 6 1 6 6","1 6 6 6 1 2","6 6 1 6 6 6"],"matched_count":26,"matched_main_count":20,"matched_other_count":6,"main_damage_multiplier":15.625,"simulation_times":10000,"combo_count_avg":7.9105,"combo_count_min":6,"main_combo_count_avg":4.9252,"main_damage_multiplier_avg":17.258},{"combo_count":7,"main_combo_count":5,"drop_times":3,"combos":[[6,5],[6,3],[6,3],[6,3],[1,5],[6,3],[1,3]],"board":["6 6 6 1 6 6","6 1 1 6 6 6","2 6 1 6 1 1","6 6 6 1 6 6","6 6 1 6 6 6"],"matched_count":25,"matched_main_count":17,"matched_other_count":8,"main_damage_multiplier":13.75,"simulation_times":10000,"combo_count_avg":8.3147,"combo_count_min":6,"main_combo_count_avg":5.4497,"main_damage_multiplier_avg":17.2537875},{"combo_count":7,"main_combo_count":5,"drop_times":4,"combos":[[6,8],[6,3],[6,3],[1,3],[6,3],[1,3],[6,3]],"board":["6 6 1 6 1 6","6 6 1 1 6 6","6 1 6 6 1 6","1 6 6 6 6 2","6 6 1 6 6 6"],"matched_count":26,"matched_main_count":20,"matched_other_count":6,"main_damage_multiplier":15.625,"simulation_times":10000,"combo_count_avg":7.9056,"combo_count_min":6,"main_combo_count_avg":4.9256,"main_damage_multiplier_avg":17.24206875},{"combo_count":7,"main_combo_count":5,"drop_times":3,"combos":[[6,5],[6,3],[6,3],[1,3],[6,3],[6,3],[1,3]],"board":["6 6 1 1 6 6","6 6 6 1 6 6","1 1 6 6 1 6","6 6 1 6 6 2","6 6 1 6 6 6"],"matched_count":23,"matched_main_count":17,"matched_other_count":6,"main_damage_multiplier":13.75,"simulation_times":10000,"combo_count_avg":8.2721,"combo_count_min":5,"main_combo_count_avg":5.3722,"main_damage_multiplier_avg":17.21431875},{"combo_count":7,"main_combo_count":5,"drop_times":3,"combos":[[6,4],[6,3],[6,3],[6,3],[1,3],[1,3],[6,3]],"board":["6 6 1 6 6 6","6 1 6 1 6 6","1 6 6 6 1 1","6 6 1 2 6 6","6 1 6 6 6 6"],"matched_count":22,"matched_main_count":16,"matched_other_count":6,"main_damage_multiplier":13.125,"simulation_times":10000,"combo_count_avg":8.4274,"combo_count_min":6,"main_combo_count_avg":5.6057,"main_damage_multiplier_avg":17.2126875},{"combo_count":7,"main_combo_count":5,"drop_times":2,"combos":[[6,3],[6,4],[6,5],[6,3],[1,3],[6,3],[1,3]],"board":["6 6 6 1 6 6","1 6 1 6 6 6","6 1 6 6 1 6","6 6 1 2 6 1","6 1 6 6 6 6"],"matched_count":24,"matched_main_count":18,"matched_other_count":6,"main_damage_multiplier":14.375,"simulation_times":10000,"combo_count_avg":8.1394,"combo_count_min":6,"main_combo_count_avg":5.3115,"main_damage_multiplier_avg":17.166575},{"combo_count":7,"main_combo_count":5,"drop_times":3,"combos":[[6,3],[6,3],[6,5],[6,3],[1,3],[6,3],[1,3]],"board":["6 6 6 2 6 6","6 6 1 6 6 6","1 1 6 1 6 1","6 6 6 1 1 6","6 6 1 6 6 6"],"matched_count":23,"matched_main_count":17,"matched_other_count":6,"main_damage_multiplier":13.75,"simulation_times":10000,"combo_count_avg":8.384,"combo_count_min":7,"main_combo_count_avg":5.4498,"main_damage_multiplier_avg":17.1324875},{"combo_count":7,"main_combo_count":5,"drop_times":2,"combos":[[6,3],[6,3],[6,6],[6,3],[1,4],[6,3],[1,3]],"board":["6 6 1 6 6 6","6 6 6 1 6 1","6 2 6 6 1 6","6 6 1 1 6 6","1 6 6 6 1 6"],"matched_count":25,"matched_main_count":18,"matched_other_count":7,"main_damage_multiplier":14.375,"simulation_times":10000,"combo_count_avg":8.1121,"combo_count_min":6,"main_combo_count_avg":5.3079,"main_damage_multiplier_avg":17.1246375},{"combo_count":7,"main_combo_count":5,"drop_times":3,"combos":[[6,5],[6,3],[6,3],[1,3],[6,3],[6,3],[1,3]],"board":["6 6 6 1 6 6","6 6 1 1 6 6","1 1 6 6 1 6","6 6 1 6 6 1","6 6 2 6 6 6"],"matched_count":23,"matched_main_count":17,"matched_other_count":6,"main_damage_multiplier":13.75,"simulation_times":10000,"combo_count_avg":8.2365,"combo_count_min":5,"main_combo_count_avg":5.3607,"main_damage_multiplier_avg":17.11295},{"combo_count":7,"main_combo_count":5,"drop_times":5,"combos":[[6,5],[6,5],[6,3],[1,3],[6,3],[1,3],[6,3]],"board":["6 1 6 6 2 6","6 6 1 6 6 1","6 1 6 1 6 6","6 6 1 6 1 6","6 6 1 6 6 6"],"matched_count":25,"matched_main_count":19,"matched_other_count":6,"main_damage_multiplier":15.0,"simulation_times":10000,"combo_count_avg":7.8417,"combo_count_min":4,"main_combo_count_avg":4.8944,"main_damage_multiplier_avg":17.094825},{"combo_count":7,"main_combo_count":5,"drop_times":3,"combos":[[6,5],[6,3],[6,3],[1,3],[6,3],[6,3],[1,3]],"board":["6 6 1 1 6 6","6 6 6 1 6 6","1 1 6 6 1 6","6 6 1 6 6 1","6 6 2 6 6 6"],"matched_count":23,"matched_main_count":17,"matched_other_count":6,"main_damage_multiplier":13.75,"simulation_times":10000,"combo_count_avg":8.2242,"combo_count_min":5,"main_combo_count_avg":5.3608,"main_damage_multiplier_avg":17.093575},{"combo_count":7,"main_combo_count":5,"drop_times":2,"combos":[[6,3],[6,3],[6,6],[6,3],[1,3],[6,3],[1,3]],"board":["6 6 1 6 6 6","6 6 6 1 6 2","6 1 6 6 1 6","6 6 1 1 6 6","1 6 6 6 1 6"],"matched_count":24,"matched_main_count":18,"matched_other_count":6,"main_damage_multiplier":14.375,"simulation_times":10000,"combo_count_avg":8.1228,"combo_count_min":7,"main_combo_count_avg":5.2923,"main_damage_multiplier_avg":17.08963125},{"combo_count":7,"main_combo_count":5,"drop_times":4,"combos":[[6,4],[6,6],[6,3],[1,3],[6,3],[1,3],[6,3]],"board":["1 6 6 6 1 6","6 6 2 6 6 1","6 1 6 1 6 6","6 6 1 6 1 6","6 1 6 6 6 6"],"matched_count":25,"matched_main_count":19,"matched_other_count":6,"main_damage_multiplier":15.0,"simulation_times":10000,"combo_count_avg":7.9196,"combo_count_min":5,"main_combo_count_avg":5.1182,"main_damage_multiplier_avg":17.0885625},{"combo_count":7,"main_combo_count":5,"drop_times":3,"combos":[[6,5],[6,3],[6,3],[6,3],[1,3],[6,3],[1,3]],"board":["6 6 6 1 6 6","6 1 2 6 6 6","1 6 1 6 1 1","6 6 6 1 6 6","6 6 1 6 6 6"],"matched_count":23,"matched_main_count":17,"matched_other_count":6,"main_damage_multiplier":13.75,"simulation_times":10000,"combo_count_avg":8.3643,"combo_count_min":7,"main_combo_count_avg":5.4356,"main_damage_multiplier_avg":17.05140625},{"combo_count":7,"main_combo_count":5,"drop_times":2,"combos":[[6,3],[6,4],[6,5],[6,3],[1,3],[6,3],[1,3]],"board":["6 6 6 1 6 6","2 6 1 6 6 6","6 1 6 6 1 6","6 6 1 1 6 1","6 1 6 6 6 6"],"matched_count":24,"matched_main_count":18,"matched_other_count":6,"main_damage_multiplier":14.375,"simulation_times":10000,"combo_count_avg":8.105,"combo_count_min":7,"main_combo_count_avg":5.2903,"main_damage_multiplier_avg":17.05106875},{"combo_count":7,"main_combo_count":5,"drop_times":2,"combos":[[6,3],[6,4],[6,5],[6,3],[1,4],[6,3],[1,3]],"board":["6 6 6 1 6 6","1 6 1 6 6 6","6 1 6 6 2 6","6 6 1 1 6 1","6 1 6 6 6 6"],"matched_count":25,"matched_main_count":18,"matched_other_count":7,"main_damage_multiplier":14.375,"simulation_times":10000,"combo_count_avg":8.0861,"combo_count_min":6,"main_combo_count_avg":5.2981,"main_damage_multiplier_avg":17.0503125},{"combo_count":7,"main_combo_count":5,"drop_times":2,"combos":[[6,3],[6,3],[6,6],[6,3],[1,4],[6,3],[1,3]],"board":["6 6 1 6 6 6","6 6 6 1 6 1","6 1 6 6 1 6","6 6 1 1 6 6","2 6 6 6 1 6"],"matched_count":25,"matched_main_count":18,"matched_other_count":7,"main_damage_multiplier":14.375,"simulation_times":10000,"combo_count_avg":8.0807,"combo_count_min":6,"main_combo_count_avg":5.2992,"main_damage_multiplier_avg":17.049125},{"combo_count":7,"main_combo_count":5,"drop_times":2,"combos":[[6,3],[6,4],[6,5],[6,3],[1,4],[6,3],[1,3]],"board":["6 6 6 1 6 6","1 6 1 6 6 6","6 1 6 6 1 6","6 6 1 1 6 2","6 1 6 6 6 6"],"matched_count":25,"matched_main_count":18,"matched_other_count":7,"main_damage_multiplier":14.375,"simulation_times":10000,"combo_count_avg":8.0826,"combo_count_min":6,"main_combo_count_avg":5.2953,"main_damage_multiplier_avg":17.03539375},{"combo_count":7,"main_combo_count":5,"drop_times":4,"combos":[[6,3],[6,6],[6,4],[1,3],[6,3],[1,3],[6,3]],"board":["6 6 6 6 1 6","1 6 2 6 6 1","6 1 6 1 6 6","6 6 1 6 1 6","6 1 6 6 6 6"],"matched_count":25,"matched_main_count":19,"matched_other_count":6,"main_damage_multiplier":15.0,"simulation_times":10000,"combo_count_avg":7.9037,"combo_count_min":5,"main_combo_count_avg":5.1132,"main_damage_multiplier_avg":17.0339125},{"combo_count":7,"main_combo_count":5,"drop_times":3,"combos":[[6,8],[6,3],[6,3],[1,3],[6,3],[1,3],[6,3]],"board":["6 1 6 6 2 6","6 6 6 1 6 6","6 6 1 6 1 6","1 6 6 1 6 1","6 6 1 6 6 6"],"matched_count":26,"matched_main_count":20,"matched_other_count":6,"main_damage_multiplier":15.625,"simulation_times":10000,"combo_count_avg":7.7513,"combo_count_min":5,"main_combo_count_avg":4.9236,"main_damage_multiplier_avg":17.0258875},{"combo_count":7,"main_combo_count":5,"drop_times":2,"combos":[[6,3],[6,3],[6,6],[6,3],[1,3],[6,3],[1,3]],"board":["6 6 1 6 6 6","6 6 6 1 6 1","6 1 6 6 1 6","6 6 2 1 6 6","1 6 6 6 1 6"],"matched_count":24,"matched_main_count":18,"matched_other_count":6,"main_damage_multiplier":14.375,"simulation_times":10000,"combo_count_avg":8.0829,"combo_count_min":6,"main_combo_count_avg":5.2939,"main_damage_multiplier_avg":17.02263125},{"combo_count":7,"main_combo_count":5,"drop_times":5,"combos":[[6,5],[6,5],[6,3],[1,3],[6,3],[1,3],[6,3]],"board":["6 2 6 6 1 6","6 6 1 6 6 1","6 1 6 1 6 6","6 6 1 6 1 6","6 6 1 6 6 6"],"matched_count":25,"matched_main_count":19,"matched_other_count":6,"main_damage_multiplier":15.0,"simulation_times":10000,"combo_count_avg":7.7828,"combo_count_min":4,"main_combo_count_avg":4.8929,"main_damage_multiplier_avg":16.99813125},{"combo_count":7,"main_combo_count":5,"drop_times":3,"combos":[[6,3],[6,5],[6,3],[1,3],[6,3],[6,3],[1,3]],"board":["6 6 6 1 6 6","6 6 1 6 6 6","6 1 6 6 1 2","1 6 6 1 1 6","6 6 1 6 6 6"],"matched_count":23,"matched_main_count":17,"matched_other_count":6,"main_damage_multiplier":13.75,"simulation_times":10000,"combo_count_avg":8.4383,"combo_count_min":7,"main_combo_count_avg":5.3755,"main_damage_multiplier_avg":16.9977},{"combo_count":7,"main_combo_count":5,"drop_times":3,"combos":[[6,3],[6,4],[6,5],[6,3],[1,3],[6,3],[1,3]],"board":["6 6 6 2 6 6","1 6 1 6 6 6","6 1 6 1 6 1","6 6 1 6 1 6","6 1 6 6 6 6"],"matched_count":24,"matched_main_count":18,"matched_other_count":6,"main_damage_multiplier":14.375,"simulation_times":10000,"combo_count_avg":8.1002,"combo_count_min":6,"main_combo_count_avg":5.2997,"main_damage_multiplier_avg":16.9893375},{"combo_count":7,"main_combo_count":5,"drop_times":4,"combos":[[6,3],[6,3],[6,7],[1,3],[6,3],[1,3],[6,3]],"board":["6 1 6 2 6 6","1 6 6 6 6 6","6 6 1 6 6 1","6 1 6 1 1 6","6 6 1 6 6 6"],"matched_count":25,"matched_main_count":19,"matched_other_count":6,"main_damage_multiplier":15.0,"simulation_times":10000,"combo_count_avg":7.9957,"combo_count_min":5,"main_combo_count_avg":5.0722,"main_damage_multiplier_avg":16.9742},{"combo_count":7,"main_combo_count":5,"drop_times":4,"combos":[[6,3],[6,3],[6,5],[6,3],[1,3],[6,3],[1,3]],"board":["6 6 6 1 6 6","6 6 2 6 6 6","1 1 6 6 1 6","6 6 6 1 6 1","6 1 1 6 6 6"],"matched_count":23,"matched_main_count":17,"matched_other_count":6,"main_damage_multiplier":13.75,"simulation_times":10000,"combo_count_avg":8.407,"combo_count_min":7,"main_combo_count_avg":5.3843,"main_damage_multiplier_avg":16.95536875},{"combo_count":7,"main_combo_count":5,"drop_times":2,"combos":[[6,3],[6,4],[6,3],[6,3],[1,4],[6,3],[1,3]],"board":["6 6 6 1 6 6","1 6 1 6 6 6","6 1 6 6 2 1","6 6 1 1 6 6","6 1 6 6 6 6"],"matched_count":23,"matched_main_count":16,"matched_other_count":7,"main_damage_multiplier":13.125,"simulation_times":10000,"combo_count_avg":8.3496,"combo_count_min":6,"main_combo_count_avg":5.5838,"main_damage_multiplier_avg":16.9538875},{"combo_count":7,"main_combo_count":5,"drop_times":4,"combos":[[6,5],[6,3],[6,3],[6,3],[1,3],[6,3],[1,3]],"board":["6 6 6 2 6 6","1 6 1 6 6 6","6 1 6 6 1 1","6 6 6 1 1 6","6 6 1 6 6 6"],"matched_count":23,"matched_main_count":17,"matched_other_count":6,"main_damage_multiplier":13.75,"simulation_times":10000,"combo_count_avg":8.3919,"combo_count_min":7,"main_combo_count_avg":5.3877,"main_damage_multiplier_avg":16.95251875},{"combo_count":7,"main_combo_count":5,"drop_times":3,"combos":[[6,8],[6,3],[6,3],[1,3],[6,3],[1,3],[6,3]],"board":["6 1 6 6 1 6","6 6 6 1 6 6","6 6 1 6 1 6","1 6 6 1 6 2","6 6 1 6 6 6"],"matched_count":26,"matched_main_count":20,"matched_other_count":6,"main_damage_multiplier":15.625,"simulation_times":10000,"combo_count_avg":7.7447,"combo_count_min":5,"main_combo_count_avg":4.9096,"main_damage_multiplier_avg":16.94768125},{"combo_count":7,"main_combo_count":5,"drop_times":3,"combos":[[6,6],[6,3],[6,3],[1,3],[6,3],[1,3],[6,3]],"board":["6 6 1 6 6 6","6 1 6 2 6 1","1 6 6 6 1 6","6 6 1 1 6 6","6 1 6 6 6 6"],"matched_count":24,"matched_main_count":18,"matched_other_count":6,"main_damage_multiplier":14.375,"simulation_times":10000,"combo_count_avg":8.0582,"combo_count_min":7,"main_combo_count_avg":5.2403,"main_damage_multiplier_avg":16.9449625},{"combo_count":7,"main_combo_count":5,"drop_times":3,"combos":[[6,3],[6,6],[6,3],[1,3],[6,3],[1,3],[6,3]],"board":["6 6 6 1 6 6","6 6 2 6 1 6","6 1 6 6 6 1","6 6 1 1 6 6","1 6 6 6 1 6"],"matched_count":24,"matched_main_count":18,"matched_other_count":6,"main_damage_multiplier":14.375,"simulation_times":10000,"combo_count_avg":8.058,"combo_count_min":7,"main_combo_count_avg":5.2384,"main_damage_multiplier_avg":16.9380125},{"combo_count":7,"main_combo_count":5,"drop_times":5,"combos":[[6,5],[6,5],[6,3],[1,3],[6,3],[1,3],[6,3]],"board":["6 1 6 6 1 6","6 6 1 6 6 1","6 2 6 1 6 6","6 6 1 6 1 6","6 6 1 6 6 6"],"matched_count":25,"matched_main_count":19,"matched_other_count":6,"main_damage_multiplier":15.0,"simulation_times":10000,"combo_count_avg":7.8275,"combo_count_min":4,"main_combo_count_avg":4.9149,"main_damage_multiplier_avg":16.92398125},{"combo_count":7,"main_combo_count":5,"drop_times":3,"combos":[[6,4],[6,3],[6,3],[6,3],[1,3],[1,3],[6,3]],"board":["6 6 1 6 6 6","6 1 6 1 6 6","1 6 6 6 1 1","6 6 1 1 6 6","6 2 6 6 6 6"],"matched_count":22,"matched_main_count":16,"matched_other_count":6,"main_damage_multiplier":13.125,"simulation_times":10000,"combo_count_avg":8.2134,"combo_count_min":6,"main_combo_count_avg":5.6042,"main_damage_multiplier_avg":16.90591875},{"combo_count":7,"main_combo_count":5,"drop_times":4,"combos":[[6,3],[6,6],[6,3],[1,3],[6,3],[1,3],[6,3]],"board":["6 6 1 1 6 6","1 6 6 2 6 6","6 1 6 6 1 6","6 6 1 6 6 1","6 1 6 6 6 6"],"matched_count":24,"matched_main_count":18,"matched_other_count":6,"main_damage_multiplier":14.375,"simulation_times":10000,"combo_count_avg":7.9163,"combo_count_min":5,"main_combo_count_avg":5.1694,"main_damage_multiplier_avg":16.8928625},{"combo_count":7,"main_combo_count":5,"drop_times":3,"combos":[[6,5],[6,3],[6,3],[1,3],[6,3],[6,3],[1,3]],"board":["6 6 6 1 6 6","6 6 1 2 6 6","1 1 6 6 1 6","6 6 1 6 6 1","6 6 1 6 6 6"],"matched_count":23,"matched_main_count":17,"matched_other_count":6,"main_damage_multiplier":13.75,"simulation_times":10000,"combo_count_avg":8.1142,"combo_count_min":5,"main_combo_count_avg":5.3729,"main_damage_multiplier_avg":16.89155},{"combo_count":7,"main_combo_count":5,"drop_times":3,"combos":[[6,5],[6,3],[6,3],[1,3],[6,3],[6,3],[1,3]],"board":["6 6 1 1 6 6","6 6 6 2 6 6","1 1 6 6 1 6","6 6 1 6 6 1","6 6 1 6 6 6"],"matched_count":23,"matched_main_count":17,"matched_other_count":6,"main_damage_multiplier":13.75,"simulation_times":10000,"combo_count_avg":8.1105,"combo_count_min":5,"main_combo_count_avg":5.3748,"main_damage_multiplier_avg":16.89130625},{"combo_count":7,"main_combo_count":5,"drop_times":4,"combos":[[6,3],[6,6],[1,3],[6,3],[6,3],[1,3],[6,3]],"board":["6 1 6 6 1 6","1 6 6 2 6 6","6 6 1 6 6 1","6 1 6 1 6 6","6 6 1 6 6 6"],"matched_count":24,"matched_main_count":18,"matched_other_count":6,"main_damage_multiplier":14.375,"simulation_times":10000,"combo_count_avg":7.9932,"combo_count_min":4,"main_combo_count_avg":5.1134,"main_damage_multiplier_avg":16.89076875},{"combo_count":7,"main_combo_count":5,"drop_times":3,"combos":[[6,4],[6,3],[6,5],[1,3],[6,3],[1,3],[6,3]],"board":["6 6 1 6 6 6","6 1 6 2 6 6","1 6 6 6 1 6","6 6 1 1 6 1","6 1 6 6 6 6"],"matched_count":24,"matched_main_count":18,"matched_other_count":6,"main_damage_multiplier":14.375,"simulation_times":10000,"combo_count_avg":8.036,"combo_count_min":7,"main_combo_count_avg":5.2274,"main_damage_multiplier_avg":16.86215},{"combo_count":7,"main_combo_count":5,"drop_times":2,"combos":[[6,3],[6,4],[6,3],[6,3],[1,4],[6,3],[1,3]],"board":["6 6 6 1 6 6","1 6 1 6 6 6","6 1 6 6 1 2","6 6 1 1 6 6","6 1 6 6 6 6"],"matched_count":23,"matched_main_count":16,"matched_other_count":7,"main_damage_multiplier":13.125,"simulation_times":10000,"combo_count_avg":8.3089,"combo_count_min":6,"main_combo_count_avg":5.5748,"main_damage_multiplier_avg":16.8538},{"combo_count":7,"main_combo_count":5,"drop_times":3,"combos":[[6,4],[6,3],[6,3],[1,3],[6,3],[1,3],[6,3]],"board":["6 6 1 6 6 6","6 1 6 2 6 6","1 6 6 6 1 1","6 6 1 1 6 6","6 1 6 6 6 6"],"matched_count":22,"matched_main_count":16,"matched_other_count":6,"main_damage_multiplier":13.125,"simulation_times":10000,"combo_count_avg":8.3887,"combo_count_min":7,"main_combo_count_avg":5.4901,"main_damage_multiplier_avg":16.837075},{"combo_count":7,"main_combo_count":5,"drop_times":3,"combos":[[6,3],[6,6],[6,3],[1,3],[6,3],[1,3],[6,3]],"board":["6 6 6 1 6 6","6 6 1 6 1 6","6 2 6 6 6 1","6 6 1 1 6 6","1 6 6 6 1 6"],"matched_count":24,"matched_main_count":18,"matched_other_count":6,"main_damage_multiplier":14.375,"simulation_times":10000,"combo_count_avg":7.9529,"combo_count_min":6,"main_combo_count_avg":5.2544,"main_damage_multiplier_avg":16.8348875},{"combo_count":7,"main_combo_count":5,"drop_times":5,"combos":[[6,5],[6,6],[6,3],[6,3],[1,3],[6,3],[1,3]],"board":["6 6 1 6 6 6","6 1 6 6 1 1","6 6 2 1 6 6","6 1 6 6 6 6","6 1 6 6 1 6"],"matched_count":26,"matched_main_count":20,"matched_other_count":6,"main_damage_multiplier":15.625,"simulation_times":10000,"combo_count_avg":7.6171,"combo_count_min":5,"main_combo_count_avg":4.8927,"main_damage_multiplier_avg":16.83351875},{"combo_count":7,"main_combo_count":5,"drop_times":3,"combos":[[6,4],[6,3],[6,3],[6,3],[1,3],[1,3],[6,3]],"board":["6 6 1 6 6 6","6 1 6 1 6 6","1 6 6 6 1 1","6 6 2 1 6 6","6 1 6 6 6 6"],"matched_count":22,"matched_main_count":16,"matched_other_count":6,"main_damage_multiplier":13.125,"simulation_times":10000,"combo_count_avg":8.196,"combo_count_min":6,"main_combo_count_avg":5.5973,"main_damage_multiplier_avg":16.8289},{"combo_count":7,"main_combo_count":5,"drop_times":3,"combos":[[6,3],[6,6],[6,3],[1,3],[6,3],[1,3],[6,3]],"board":["6 6 6 1 6 6","6 6 1 6 1 6","6 1 6 6 6 1","6 6 1 1 6 6","2 6 6 6 1 6"],"matched_count":24,"matched_main_count":18,"matched_other_count":6,"main_damage_multiplier":14.375,"simulation_times":10000,"combo_count_avg":7.9165,"combo_count_min":6,"main_combo_count_avg":5.2703,"main_damage_multiplier_avg":16.8288},{"combo_count":7,"main_combo_count":5,"drop_times":3,"combos":[[6,3],[6,3],[6,5],[6,3],[1,3],[6,3],[1,3]],"board":["6 6 6 1 6 6","6 6 1 6 6 6","1 2 6 6 1 6","6 6 6 1 6 1","6 1 1 6 6 6"],"matched_count":23,"matched_main_count":17,"matched_other_count":6,"main_damage_multiplier":13.75,"simulation_times":10000,"combo_count_avg":8.3141,"combo_count_min":7,"main_combo_count_avg":5.3675,"main_damage_multiplier_avg":16.77874375},{"combo_count":7,"main_combo_count":5,"drop_times":5,"combos":[[6,5],[6,4],[6,5],[6,3],[1,3],[6,3],[1,3]],"board":["6 6 1 6 6 6","6 1 6 6 1 6","6 6 2 1 6 6","6 1 6 6 1 1","6 1 6 6 6 6"],"matched_count":26,"matched_main_count":20,"matched_other_count":6,"main_damage_multiplier":15.625,"simulation_times":10000,"combo_count_avg":7.5997,"combo_count_min":5,"main_combo_count_avg":4.8792,"main_damage_multiplier_avg":16.7748625},{"combo_count":7,"main_combo_count":5,"drop_times":3,"combos":[[6,3],[6,3],[6,5],[6,3],[1,3],[6,3],[1,3]],"board":["6 6 6 1 6 6","6 6 1 6 6 6","2 1 6 6 1 6","6 6 6 1 6 1","6 1 1 6 6 6"],"matched_count":23,"matched_main_count":17,"matched_other_count":6,"main_damage_multiplier":13.75,"simulation_times":10000,"combo_count_avg":8.3224,"combo_count_min":7,"main_combo_count_avg":5.3613,"main_damage_multiplier_avg":16.77085},{"combo_count":7,"main_combo_count":5,"drop_times":5,"combos":[[6,3],[6,5],[6,6],[6,3],[1,3],[6,3],[1,3]],"board":["6 6 6 1 6 6","6 1 6 6 1 6","6 6 1 2 6 6","6 1 6 6 1 6","1 6 6 6 1 6"],"matched_count":26,"matched_main_count":20,"matched_other_count":6,"main_damage_multiplier":15.625,"simulation_times":10000,"combo_count_avg":7.5894,"combo_count_min":5,"main_combo_count_avg":4.8773,"main_damage_multiplier_avg":16.76586875},{"combo_count":7,"main_combo_count":5,"drop_times":5,"combos":[[6,5],[6,6],[6,3],[6,3],[1,3],[6,3],[1,3]],"board":["6 6 1 6 6 6","6 1 6 6 1 1","6 6 2 1 6 6","6 1 6 6 1 6","6 1 6 6 6 6"],"matched_count":26,"matched_main_count":20,"matched_other_count":6,"main_damage_multiplier":15.625,"simulation_times":10000,"combo_count_avg":7.591,"combo_count_min":5,"main_combo_count_avg":4.8823,"main_damage_multiplier_avg":16.76283125},{"combo_count":7,"main_combo_count":5,"drop_times":3,"combos":[[6,5],[6,3],[6,3],[6,3],[1,3],[6,3],[1,3]],"board":["6 6 6 1 6 6","1 6 1 6 6 6","6 1 6 6 2 1","6 6 6 1 1 6","6 6 1 6 6 6"],"matched_count":23,"matched_main_count":17,"matched_other_count":6,"main_damage_multiplier":13.75,"simulation_times":10000,"combo_count_avg":8.3247,"combo_count_min":7,"main_combo_count_avg":5.3581,"main_damage_multiplier_avg":16.7558875},{"combo_count":7,"main_combo_count":5,"drop_times":3,"combos":[[6,4],[6,3],[6,5],[1,3],[6,3],[1,3],[6,3]],"board":["6 6 1 6 6 6","6 1 6 1 6 6","1 6 6 6 1 6","6 6 1 1 6 2","6 1 6 6 6 6"],"matched_count":24,"matched_main_count":18,"matched_other_count":6,"main_damage_multiplier":14.375,"simulation_times":10000,"combo_count_avg":7.901,"combo_count_min":6,"main_combo_count_avg":5.2576,"main_damage_multiplier_avg":16.7549375},{"combo_count":7,"main_combo_count":5,"drop_times":3,"combos":[[6,6],[6,3],[6,3],[1,3],[6,3],[1,3],[6,3]],"board":["6 6 1 6 6 6","6 1 6 1 6 2","1 6 6 6 1 6","6 6 1 1 6 6","6 1 6 6 6 6"],"matched_count":24,"matched_main_count":18,"matched_other_count":6,"main_damage_multiplier":14.375,"simulation_times":10000,"combo_count_avg":7.8973,"combo_count_min":6,"main_combo_count_avg":5.258,"main_damage_multiplier_avg":16.75475625},{"combo_count":7,"main_combo_count":5,"drop_times":4,"combos":[[6,3],[6,6],[6,3],[6,3],[1,3],[1,4],[6,3]],"board":["6 6 6 1 6 6","1 6 1 2 6 6","6 1 6 6 1 6","6 6 1 6 6 1","6 1 6 6 6 6"],"matched_count":25,"matched_main_count":18,"matched_other_count":7,"main_damage_multiplier":14.375,"simulation_times":10000,"combo_count_avg":7.994,"combo_count_min":5,"main_combo_count_avg":5.2235,"main_damage_multiplier_avg":16.7501375},{"combo_count":7,"main_combo_count":5,"drop_times":3,"combos":[[6,4],[6,3],[6,5],[1,3],[6,3],[1,3],[6,3]],"board":["6 6 1 6 6 6","6 1 6 1 6 6","1 6 6 6 2 6","6 6 1 1 6 1","6 1 6 6 6 6"],"matched_count":24,"matched_main_count":18,"matched_other_count":6,"main_damage_multiplier":14.375,"simulation_times":10000,"combo_count_avg":7.9275,"combo_count_min":6,"main_combo_count_avg":5.2442,"main_damage_multiplier_avg":16.74996875},{"combo_count":7,"main_combo_count":5,"drop_times":3,"combos":[[6,6],[6,3],[6,3],[1,3],[6,3],[1,3],[6,3]],"board":["6 6 1 6 6 6","6 1 6 1 6 1","1 6 6 6 2 6","6 6 1 1 6 6","6 1 6 6 6 6"],"matched_count":24,"matched_main_count":18,"matched_other_count":6,"main_damage_multiplier":14.375,"simulation_times":10000,"combo_count_avg":7.9145,"combo_count_min":6,"main_combo_count_avg":5.2384,"main_damage_multiplier_avg":16.7316375},{"combo_count":7,"main_combo_count":5,"drop_times":3,"combos":[[6,5],[6,3],[6,3],[6,3],[1,3],[6,3],[1,3]],"board":["6 6 6 1 6 6","1 6 1 6 6 6","6 1 6 6 1 2","6 6 6 1 1 6","6 6 1 6 6 6"],"matched_count":23,"matched_main_count":17,"matched_other_count":6,"main_damage_multiplier":13.75,"simulation_times":10000,"combo_count_avg":8.3029,"combo_count_min":7,"main_combo_count_avg":5.3551,"main_damage_multiplier_avg":16.71325625},{"combo_count":7,"main_combo_count":5,"drop_times":4,"combos":[[6,3],[6,3],[6,6],[1,3],[6,3],[1,3],[6,3]],"board":["6 1 6 6 6 6","1 6 6 2 6 6","6 6 1 6 6 1","6 1 6 1 1 6","6 6 1 6 6 6"],"matched_count":24,"matched_main_count":18,"matched_other_count":6,"main_damage_multiplier":14.375,"simulation_times":10000,"combo_count_avg":8.0657,"combo_count_min":5,"main_combo_count_avg":5.1669,"main_damage_multiplier_avg":16.70598125},{"combo_count":7,"main_combo_count":5,"drop_times":3,"combos":[[6,5],[6,3],[6,3],[6,3],[1,3],[6,3],[1,3]],"board":["6 6 6 1 6 6","2 6 1 6 6 6","6 1 6 6 1 1","6 6 6 1 1 6","6 6 1 6 6 6"],"matched_count":23,"matched_main_count":17,"matched_other_count":6,"main_damage_multiplier":13.75,"simulation_times":10000,"combo_count_avg":8.2944,"combo_count_min":7,"main_combo_count_avg":5.3551,"main_damage_multiplier_avg":16.7015},{"combo_count":7,"main_combo_count":5,"drop_times":3,"combos":[[6,3],[6,3],[6,3],[6,3],[1,3],[6,4],[1,4]],"board":["6 6 6 1 6 6","6 6 1 6 6 6","2 1 6 6 1 1","6 6 6 1 6 6","6 1 1 6 6 6"],"matched_count":23,"matched_main_count":16,"matched_other_count":7,"main_damage_multiplier":13.125,"simulation_times":10000,"combo_count_avg":8.4295,"combo_count_min":7,"main_combo_count_avg":5.5077,"main_damage_multiplier_avg":16.6726625},{"combo_count":7,"main_combo_count":5,"drop_times":2,"combos":[[6,3],[6,4],[6,3],[6,3],[1,3],[6,3],[1,3]],"board":["6 6 6 1 6 6","1 6 1 6 6 6","6 1 6 6 1 1","6 6 1 2 6 6","6 1 6 6 6 6"],"matched_count":22,"matched_main_count":16,"matched_other_count":6,"main_damage_multiplier":13.125,"simulation_times":10000,"combo_count_avg":8.3935,"combo_count_min":6,"main_combo_count_avg":5.4717,"main_damage_multiplier_avg":16.67055625},{"combo_count":7,"main_combo_count":5,"drop_times":3,"combos":[[6,3],[6,3],[6,5],[6,3],[1,3],[6,3],[1,3]],"board":["6 6 6 1 6 6","6 6 1 6 6 6","1 1 6 6 1 6","6 6 6 1 6 2","6 1 1 6 6 6"],"matched_count":23,"matched_main_count":17,"matched_other_count":6,"main_damage_multiplier":13.75,"simulation_times":10000,"combo_count_avg":8.2709,"combo_count_min":7,"main_combo_count_avg":5.3566,"main_damage_multiplier_avg":16.66925625},{"combo_count":7,"main_combo_count":5,"drop_times":4,"combos":[[6,6],[6,3],[6,3],[1,3],[6,3],[1,3],[6,3]],"board":["6 6 1 6 1 6","6 6 2 6 6 6","6 1 6 1 6 1","1 6 6 6 1 6","6 6 1 6 6 6"],"matched_count":24,"matched_main_count":18,"matched_other_count":6,"main_damage_multiplier":14.375,"simulation_times":10000,"combo_count_avg":8.1162,"combo_count_min":6,"main_combo_count_avg":5.1507,"main_damage_multiplier_avg":16.66778125},{"combo_count":7,"main_combo_count":5,"drop_times":3,"combos":[[6,3],[6,3],[6,3],[6,3],[1,3],[6,4],[1,3]],"board":["6 6 6 1 6 6","6 6 1 6 6 6","2 1 6 6 1 1","6 6 6 1 1 6","6 6 1 6 6 6"],"matched_count":22,"matched_main_count":16,"matched_other_count":6,"main_damage_multiplier":13.125,"simulation_times":10000,"combo_count_avg":8.4148,"combo_count_min":7,"main_combo_count_avg":5.5079,"main_damage_multiplier_avg":16.66433125},{"combo_count":7,"main_combo_count":5,"drop_times":4,"combos":[[6,6],[6,3],[6,3],[1,3],[6,3],[1,3],[6,3]],"board":["6 6 1 6 6 6","6 6 2 6 1 6","6 1 6 1 6 1","1 6 6 6 1 6","6 6 1 6 6 6"],"matched_count":24,"matched_main_count":18,"matched_other_count":6,"main_damage_multiplier":14.375,"simulation_times":10000,"combo_count_avg":8.1143,"combo_count_min":6,"main_combo_count_avg":5.1518,"main_damage_multiplier_avg":16.66331875},{"combo_count":7,"main_combo_count":5,"drop_times":3,"combos":[[6,3],[6,3],[6,3],[6,3],[1,3],[6,4],[1,4]],"board":["6 6 6 1 6 6","6 6 1 6 6 6","1 1 6 6 2 1","6 6 6 1 1 6","6 6 1 6 6 6"],"matched_count":23,"matched_main_count":16,"matched_other_count":7,"main_damage_multiplier":13.125,"simulation_times":10000,"combo_count_avg":8.4143,"combo_count_min":7,"main_combo_count_avg":5.5015,"main_damage_multiplier_avg":16.6386875},{"combo_count":7,"main_combo_count":5,"drop_times":3,"combos":[[6,3],[6,3],[6,3],[6,3],[1,3],[6,4],[1,3]],"board":["6 6 6 2 6 6","6 6 1 6 6 6","1 1 6 6 1 1","6 6 6 1 1 6","6 6 1 6 6 6"],"matched_count":22,"matched_main_count":16,"matched_other_count":6,"main_damage_multiplier":13.125,"simulation_times":10000,"combo_count_avg":8.3998,"combo_count_min":7,"main_combo_count_avg":5.4989,"main_damage_multiplier_avg":16.59849375},{"combo_count":7,"main_combo_count":5,"drop_times":3,"combos":[[6,3],[6,3],[6,3],[6,3],[1,3],[6,4],[1,4]],"board":["6 6 6 1 6 6","6 6 1 6 6 6","1 1 6 6 1 2","6 6 6 1 1 6","6 6 1 6 6 6"],"matched_count":23,"matched_main_count":16,"matched_other_count":7,"main_damage_multiplier":13.125,"simulation_times":10000,"combo_count_avg":8.3847,"combo_count_min":7,"main_combo_count_avg":5.501,"main_damage_multiplier_avg":16.594875},{"combo_count":7,"main_combo_count":5,"drop_times":3,"combos":[[6,3],[6,3],[6,3],[6,3],[1,3],[6,4],[1,3]],"board":["6 6 6 1 6 6","6 6 1 6 6 6","1 1 6 6 1 2","6 6 6 1 6 6","6 1 1 6 6 6"],"matched_count":22,"matched_main_count":16,"matched_other_count":6,"main_damage_multiplier":13.125,"simulation_times":10000,"combo_count_avg":8.3884,"combo_count_min":7,"main_combo_count_avg":5.5,"main_damage_multiplier_avg":16.59355},{"combo_count":7,"main_combo_count":5,"drop_times":4,"combos":[[6,3],[6,5],[6,4],[1,3],[6,3],[1,3],[6,3]],"board":["6 1 6 6 6 6","1 6 6 2 1 6","6 6 1 6 6 1","6 1 6 1 6 6","6 6 1 6 6 6"],"matched_count":24,"matched_main_count":18,"matched_other_count":6,"main_damage_multiplier":14.375,"simulation_times":10000,"combo_count_avg":8.0262,"combo_count_min":5,"main_combo_count_avg":5.149,"main_damage_multiplier_avg":16.5903875},{"combo_count":7,"main_combo_count":5,"drop_times":3,"combos":[[6,3],[6,3],[6,3],[6,3],[1,3],[6,4],[1,4]],"board":["6 6 6 1 6 6","6 6 1 6 6 6","1 2 6 6 1 1","6 6 6 1 6 6","6 1 1 6 6 6"],"matched_count":23,"matched_main_count":16,"matched_other_count":7,"main_damage_multiplier":13.125,"simulation_times":10000,"combo_count_avg":8.3981,"combo_count_min":7,"main_combo_count_avg":5.4893,"main_damage_multiplier_avg":16.5805375},{"combo_count":7,"main_combo_count":5,"drop_times":3,"combos":[[6,3],[6,3],[6,3],[6,3],[1,3],[6,4],[1,3]],"board":["6 6 6 1 6 6","6 6 2 6 6 6","1 1 6 6 1 1","6 6 6 1 6 6","6 1 1 6 6 6"],"matched_count":22,"matched_main_count":16,"matched_other_count":6,"main_damage_multiplier":13.125,"simulation_times":10000,"combo_count_avg":8.3901,"combo_count_min":7,"main_combo_count_avg":5.4914,"main_damage_multiplier_avg":16.5580625},{"combo_count":7,"main_combo_count":5,"drop_times":3,"combos":[[6,3],[6,5],[6,3],[1,3],[6,3],[6,3],[1,3]],"board":["6 6 6 2 6 6","6 6 1 6 6 6","6 1 6 6 1 1","1 6 6 1 1 6","6 6 1 6 6 6"],"matched_count":23,"matched_main_count":17,"matched_other_count":6,"main_damage_multiplier":13.75,"simulation_times":10000,"combo_count_avg":8.1984,"combo_count_min":7,"main_combo_count_avg":5.3426,"main_damage_multiplier_avg":16.53301875},{"combo_count":7,"main_combo_count":5,"drop_times":3,"combos":[[6,4],[6,3],[6,3],[1,3],[6,3],[1,3],[6,3]],"board":["6 6 1 6 6 6","6 1 6 1 6 6","1 6 6 6 1 2","6 6 1 1 6 6","6 1 6 6 6 6"],"matched_count":22,"matched_main_count":16,"matched_other_count":6,"main_damage_multiplier":13.125,"simulation_times":10000,"combo_count_avg":8.1462,"combo_count_min":6,"main_combo_count_avg":5.5053,"main_damage_multiplier_avg":16.51855},{"combo_count":7,"main_combo_count":5,"drop_times":3,"combos":[[6,4],[6,3],[6,3],[1,3],[6,3],[1,3],[6,3]],"board":["6 6 1 6 6 6","6 1 6 1 6 6","1 6 6 6 2 1","6 6 1 1 6 6","6 1 6 6 6 6"],"matched_count":22,"matched_main_count":16,"matched_other_count":6,"main_damage_multiplier":13.125,"simulation_times":10000,"combo_count_avg":8.1571,"combo_count_min":6,"main_combo_count_avg":5.501,"main_damage_multiplier_avg":16.51129375},{"combo_count":7,"main_combo_count":5,"drop_times":3,"combos":[[6,3],[6,5],[6,3],[1,3],[6,3],[6,3],[1,3]],"board":["6 6 6 1 6 6","6 6 1 6 6 6","6 1 6 6 2 1","1 6 6 1 1 6","6 6 1 6 6 6"],"matched_count":23,"matched_main_count":17,"matched_other_count":6,"main_damage_multiplier":13.75,"simulation_times":10000,"combo_count_avg":8.203,"combo_count_min":7,"main_combo_count_avg":5.3288,"main_damage_multiplier_avg":16.497825},{"combo_count":7,"main_combo_count":5,"drop_times":4,"combos":[[6,6],[6,3],[6,3],[1,3],[6,3],[1,3],[6,3]],"board":["6 6 1 6 6 6","6 6 1 6 2 6","6 1 6 1 6 1","1 6 6 6 1 6","6 6 1 6 6 6"],"matched_count":24,"matched_main_count":18,"matched_other_count":6,"main_damage_multiplier":14.375,"simulation_times":10000,"combo_count_avg":8.0191,"combo_count_min":6,"main_combo_count_avg":5.0707,"main_damage_multiplier_avg":16.34335},{"combo_count":7,"main_combo_count":5,"drop_times":4,"combos":[[6,6],[6,3],[6,3],[1,3],[6,3],[1,3],[6,3]],"board":["6 6 1 6 2 6","6 6 1 6 6 6","6 1 6 1 6 1","1 6 6 6 1 6","6 6 1 6 6 6"],"matched_count":24,"matched_main_count":18,"matched_other_count":6,"main_damage_multiplier":14.375,"simulation_times":10000,"combo_count_avg":7.9924,"combo_count_min":6,"main_combo_count_avg":5.0681,"main_damage_multiplier_avg":16.28},{"combo_count":7,"main_combo_count":5,"drop_times":4,"combos":[[6,4],[6,6],[6,3],[1,3],[1,4],[6,3],[6,3]],"board":["1 6 6 1 6 6","6 6 1 2 6 6","6 1 6 6 1 6","6 6 1 6 6 1","6 1 6 6 6 6"],"matched_count":26,"matched_main_count":19,"matched_other_count":7,"main_damage_multiplier":15.0,"simulation_times":10000,"combo_count_avg":7.5424,"combo_count_min":5,"main_combo_count_avg":4.7774,"main_damage_multiplier_avg":15.98149375},{"combo_count":7,"main_combo_count":5,"drop_times":5,"combos":[[6,7],[6,3],[6,3],[1,4],[6,3],[1,3],[6,3]],"board":["6 6 6 1 6 6","1 1 6 6 1 6","6 6 1 6 6 1","6 6 6 1 2 6","6 6 1 6 6 6"],"matched_count":26,"matched_main_count":19,"matched_other_count":7,"main_damage_multiplier":15.0,"simulation_times":10000,"combo_count_avg":7.6163,"combo_count_min":4,"main_combo_count_avg":4.9072,"main_damage_multiplier_avg":15.968975},{"combo_count":7,"main_combo_count":5,"drop_times":4,"combos":[[6,6],[6,3],[6,3],[1,3],[6,3],[1,3],[6,3]],"board":["6 6 1 6 1 6","6 6 1 6 6 6","6 1 6 1 6 2","1 6 6 6 1 6","6 6 1 6 6 6"],"matched_count":24,"matched_main_count":18,"matched_other_count":6,"main_damage_multiplier":14.375,"simulation_times":10000,"combo_count_avg":7.8977,"combo_count_min":6,"main_combo_count_avg":4.9823,"main_damage_multiplier_avg":15.93174375},{"combo_count":7,"main_combo_count":5,"drop_times":4,"combos":[[6,6],[6,3],[6,3],[1,3],[6,3],[1,3],[6,3]],"board":["6 6 1 6 6 6","6 6 1 6 1 6","6 1 6 1 6 2","1 6 6 6 1 6","6 6 1 6 6 6"],"matched_count":24,"matched_main_count":18,"matched_other_count":6,"main_damage_multiplier":14.375,"simulation_times":10000,"combo_count_avg":7.8336,"combo_count_min":6,"main_combo_count_avg":4.9689,"main_damage_multiplier_avg":15.78934375},{"combo_count":7,"main_combo_count":5,"drop_times":5,"combos":[[6,5],[6,3],[6,3],[1,3],[6,3],[1,3],[6,3]],"board":["6 6 6 1 6 6","6 1 6 6 1 6","1 6 1 6 6 1","6 6 6 1 2 6","6 6 1 6 6 6"],"matched_count":23,"matched_main_count":17,"matched_other_count":6,"main_damage_multiplier":13.75,"simulation_times":10000,"combo_count_avg":7.327,"combo_count_min":4,"main_combo_count_avg":4.8056,"main_damage_multiplier_avg":14.175625}]}}