{"orb_combination":[22,7,1],"combo_threshold":6,"threads":4,"cost_time":162.9531672000885,"max_combo":7,"combo_to_board_count":{"6":602,"7":3},"combo_to_boards":{"7":[{"combo_count":7,"main_combo_count":5,"drop_times":4,"combos":[[6,9],[6,3],[6,3],[1,4],[6,3],[1,3],[6,3]],"matched_count":28,"matched_main_count":21,"matched_other_count":7,"board":["6 6 1 6 6 6","6 6 2 6 6 1","6 1 6 1 1 6","1 6 6 6 6 6","6 6 1 6 6 6"],"simulation_times":1000,"combo_count_avg":8.216,"combo_count_min":6,"main_combo_count_avg":5.104,"main_damage_multiplier_avg":18.97125},{"combo_count":7,"main_combo_count":5,"drop_times":4,"combos":[[6,9],[6,3],[6,3],[1,3],[6,3],[1,3],[6,3]],"matched_count":27,"matched_main_count":21,"matched_other_count":6,"board":["6 6 1 6 6 6","6 6 1 6 6 2","6 1 6 1 1 6","1 6 6 6 6 6","6 6 1 6 6 6"],"simulation_times":1000,"combo_count_avg":8.122,"combo_count_min":6,"main_combo_count_avg":5.019,"main_damage_multiplier_avg":18.5781875},{"combo_count":7,"main_combo_count":5,"drop_times":4,"combos":[[6,9],[6,3],[6,3],[1,3],[6,3],[1,3],[6,3]],"matched_count":27,"matched_main_count":21,"matched_other_count":6,"board":["6 6 1 6 6 6","6 6 1 6 6 1","6 1 6 1 1 6","1 6 6 6 6 6","6 6 2 6 6 6"],"simulation_times":1000,"combo_count_avg":8.108,"combo_count_min":6,"main_combo_count_avg":5.027,"main_damage_multiplier_avg":18.5420625}]}}